Workbook

Sheet Dashboard
A1: PUROY SALON — OPERATIONAL & FINANCIAL DASHBOARD (JAN 2024 – DEC 2025)
A2: Overview of revenue, sessions, expenses, and net income across the 2-year model. Navigate using the sheet tabs for detailed daily/weekly/monthly/quarterly/biannual/annual breakdowns, MoM & YoY comparisons, AM/PM demand, ABC analysis, and inventory tracking.
A4: Total Revenue (2024-2025) | C4: Total Sessions | E4: Total Net Income | G4: Average Net Margin | I4: 2025 vs 2024 Revenue Growth (YoY)
A5: =SUM('Daily Data'!G4:G734) -> 3053476 | C5: =SUM('Daily Data'!D4:D734) -> 5751 | E5: =SUM('Daily Data'!P4:P734) -> 2085544 | G5: =SUM('Daily Data'!P4:P734)/SUM('Daily Data'!G4:G734) -> 0.68300651 | I5: ='Annual & YoY'!G5 -> -0.016179939
A7: SEASONAL PEAK & LOW PERIODS
A8: Period Type | B8: Months | C8: Avg Monthly Revenue (₱) | D8: Characteristics
A9: 🟢 PEAK | B9: December, March-May | C9: =AVERAGEIFS('Monthly Trends'!D4:D27,'Monthly Trends'!K4:K27,"Peak") -> 164010.75 | D9: Holiday season (Dec) and summer/vacation season (Mar-May) drive highest demand for long-duration chemical services and walk-ins.
A10: 🔴 LOW | B10: June-September | C10: =AVERAGEIFS('Monthly Trends'!D4:D27,'Monthly Trends'!K4:K27,"Low") -> 102961.88 | D10: Rainy season reduces walk-in traffic; clients defer non-essential salon visits.
A11: ⚪ NORMAL | B11: January, February, October, November | C11: =AVERAGEIFS('Monthly Trends'!D4:D27,'Monthly Trends'!K4:K27,"Normal") -> 114711.88 | D11: Baseline demand; January reflects a post-holiday spending dip.

Sheet Daily Data
A1: PUROY SALON — DAILY OPERATIONS DATA (JAN 1, 2024 – DEC 31, 2025)
A2: Source: Nov 2024-Apr 2025 monthly totals & Jan 1-May 29, 2025 daily records (actual). Remaining periods are model-generated using day-of-week traffic patterns, seasonal demand (peaks: December holidays & summer Mar-May; lows: rainy season Jun-Sep), and year-on-year growth assumptions. | T2: Rebond, Cello, Haircut | V2: Rebond, Cello + Brazilian Collagen | X2: Protein Straightening Treatment | Z2: Brazilian Collagen / Hair Botox | AB2: Hair Color / Cellophane Treatment | AD2: Cold Wave Perm | AF2: Keratin Opti Straight | AH2: Haircut | AJ2: Kilay (Eyebrow) | AL2: Manicure | AN2: Pedicure | AP2: Foot Spa
A3: Date | B3: Day | C3: Day Type | D3: Sessions | E3: AM Sessions | F3: PM Sessions | G3: Revenue (₱) | H3: AM Revenue (₱) | I3: PM Revenue (₱) | J3: Electricity (₱) | K3: Water (₱) | L3: Salary (₱) | M3: Commission (₱) | N3: Supplies (₱) | O3: Total Expenses (₱) | P3: Net Income (₱) | Q3: Top Service | T3: Sessions | U3: Revenue (₱) | V3: Sessions | W3: Revenue (₱) | X3: Sessions | Y3: Revenue (₱) | Z3: Sessions | AA3: Revenue (₱) | AB3: Sessions | AC3: Revenue (₱) | AD3: Sessions | AE3: Revenue (₱) | AF3: Sessions | AG3: Revenue (₱) | AH3: Sessions | AI3: Revenue (₱) | AJ3: Sessions | AK3: Revenue (₱) | AL3: Sessions | AM3: Revenue (₱) | AN3: Sessions | AO3: Revenue (₱) | AP3: Sessions | AQ3: Revenue (₱)
A4: 45292 | B4: Monday | C4: Weekday | D4: 0 | E4: 0 | F4: 0 | G4: 0 | H4: 0 | I4: 0 | J4: 232 | K4: 97 | L4: 806 | M4: 0 | N4: 0 | O4: =SUM(J4:N4) -> 1135 | P4: =G4-O4 -> -1135 | Q4: CLOSED | R4: Low (Post-Holiday) | T4: 0 | U4: 0 | V4: 0 | W4: 0 | X4: 0 | Y4: 0 | Z4: 0 | AA4: 0 | AB4: 0 | AC4: 0 | AD4: 0 | AE4: 0 | AF4: 0 | AG4: 0 | AH4: 0 | AI4: 0 | AJ4: 0 | AK4: 0 | AL4: 0 | AM4: 0 | AN4: 0 | AO4: 0 | AP4: 0 | AQ4: 0
A5: 45293 | B5: Tuesday | C5: Weekday | D5: 6 | E5: 2 | F5: 4 | G5: 2883 | H5: 2228 | I5: 655 | J5: 232 | K5: 97 | L5: 806 | M5: 64 | N5: 49 | O5: =SUM(J5:N5) -> 1248 | P5: =G5-O5 -> 1635 | Q5: Rebond, Cello, Haircut | R5: Low (Post-Holiday) | T5: 1 | U5: 1442 | V5: 0 | W5: 0 | X5: 0 | Y5: 0 | Z5: 0 | AA5: 0 | AB5: 1 | AC5: 786 | AD5: 0 | AE5: 0 | AF5: 0 | AG5: 0 | AH5: 1 | AI5: 183 | AJ5: 1 | AK5: 92 | AL5: 1 | AM5: 183 | AN5: 1 | AO5: 197 | AP5: 0 | AQ5: 0
A6: 45294 | B6: Wednesday | C6: Weekday | D6: 6 | E6: 2 | F6: 4 | G6: 2888 | H6: 2232 | I6: 656 | J6: 232 | K6: 97 | L6: 806 | M6: 64 | N6: 49 | O6: =SUM(J6:N6) -> 1248 | P6: =G6-O6 -> 1640 | Q6: Rebond, Cello, Haircut | R6: Low (Post-Holiday) | T6: 1 | U6: 1444 | V6: 0 | W6: 0 | X6: 0 | Y6: 0 | Z6: 0 | AA6: 0 | AB6: 1 | AC6: 788 | AD6: 0 | AE6: 0 | AF6: 0 | AG6: 0 | AH6: 1 | AI6: 184 | AJ6: 1 | AK6: 92 | AL6: 1 | AM6: 184 | AN6: 1 | AO6: 197 | AP6: 0 | AQ6: 0
A7: 45295 | B7: Thursday | C7: Weekday | D7: 6 | E7: 2 | F7: 4 | G7: 3229 | H7: 2495 | I7: 734 | J7: 232 | K7: 97 | L7: 806 | M7: 71 | N7: 49 | O7: =SUM(J7:N7) -> 1255 | P7: =G7-O7 -> 1974 | Q7: Rebond, Cello, Haircut | R7: Low (Post-Holiday) | T7: 1 | U7: 1614 | V7: 0 | W7: 0 | X7: 0 | Y7: 0 | Z7: 0 | AA7: 0 | AB7: 1 | AC7: 881 | AD7: 0 | AE7: 0 | AF7: 0 | AG7: 0 | AH7: 1 | AI7: 205 | AJ7: 1 | AK7: 103 | AL7: 1 | AM7: 205 | AN7: 1 | AO7: 220 | AP7: 0 | AQ7: 0
A8: 45296 | B8: Friday | C8: Weekday | D8: 6 | E8: 2 | F8: 4 | G8: 3306 | H8: 2555 | I8: 751 | J8: 232 | K8: 97 | L8: 806 | M8: 73 | N8: 49 | O8: =SUM(J8:N8) -> 1257 | P8: =G8-O8 -> 2049 | Q8: Rebond, Cello, Haircut | R8: Low (Post-Holiday) | T8: 1 | U8: 1653 | V8: 0 | W8: 0 | X8: 0 | Y8: 0 | Z8: 0 | AA8: 0 | AB8: 1 | AC8: 902 | AD8: 0 | AE8: 0 | AF8: 0 | AG8: 0 | AH8: 1 | AI8: 210 | AJ8: 1 | AK8: 105 | AL8: 1 | AM8: 210 | AN8: 1 | AO8: 225 | AP8: 0 | AQ8: 0
A9: 45297 | B9: Saturday | C9: Weekend | D9: 7 | E9: 2 | F9: 5 | G9: 3847 | H9: 2669 | I9: 1178 | J9: 232 | K9: 97 | L9: 806 | M9: 85 | N9: 57 | O9: =SUM(J9:N9) -> 1277 | P9: =G9-O9 -> 2570 | Q9: Rebond, Cello, Haircut | R9: Low (Post-Holiday) | T9: 1 | U9: 1727 | V9: 0 | W9: 0 | X9: 0 | Y9: 0 | Z9: 0 | AA9: 0 | AB9: 1 | AC9: 942 | AD9: 0 | AE9: 0 | AF9: 0 | AG9: 0 | AH9: 1 | AI9: 220 | AJ9: 1 | AK9: 110 | AL9: 1 | AM9: 220 | AN9: 1 | AO9: 236 | AP9: 1 | AQ9: 393
A10: 45298 | B10: Sunday | C10: Weekend | D10: 7 | E10: 2 | F10: 5 | G10: 3554 | H10: 2466 | I10: 1088 | J10: 232 | K10: 97 | L10: 806 | M10: 78 | N10: 57 | O10: =SUM(J10:N10) -> 1270 | P10: =G10-O10 -> 2284 | Q10: Rebond, Cello, Haircut | R10: Low (Post-Holiday) | T10: 1 | U10: 1596 | V10: 0 | W10: 0 | X10: 0 | Y10: 0 | Z10: 0 | AA10: 0 | AB10: 1 | AC10: 870 | AD10: 0 | AE10: 0 | AF10: 0 | AG10: 0 | AH10: 1 | AI10: 203 | AJ10: 1 | AK10: 102 | AL10: 1 | AM10: 203 | AN10: 1 | AO10: 218 | AP10: 1 | AQ10: 363
A11: 45299 | B11: Monday | C11: Weekday | D11: 5 | E11: 1 | F11: 4 | G11: 2557 | H11: 1395 | I11: 1162 | J11: 232 | K11: 97 | L11: 806 | M11: 56 | N11: 40 | O11: =SUM(J11:N11) -> 1231 | P11: =G11-O11 -> 1326 | Q11: Hair Color / Cellophane Treatment | R11: Low (Post-Holiday) | T11: 0 | U11: 0 | V11: 0 | W11: 0 | X11: 0 | Y11: 0 | Z11: 0 | AA11: 0 | AB11: 1 | AC11: 1395 | AD11: 0 | AE11: 0 | AF11: 0 | AG11: 0 | AH11: 1 | AI11: 325 | AJ11: 1 | AK11: 163 | AL11: 1 | AM11: 325 | AN11: 1 | AO11: 349 | AP11: 0 | AQ11: 0
A12: 45300 | B12: Tuesday | C12: Weekday | D12: 6 | E12: 2 | F12: 4 | G12: 2980 | H12: 2303 | I12: 677 | J12: 232 | K12: 97 | L12: 806 | M12: 66 | N12: 49 | O12: =SUM(J12:N12) -> 1250 | P12: =G12-O12 -> 1730 | Q12: Rebond, Cello, Haircut | R12: Low (Post-Holiday) | T12: 1 | U12: 1490 | V12: 0 | W12: 0 | X12: 0 | Y12: 0 | Z12: 0 | AA12: 0 | AB12: 1 | AC12: 813 | AD12: 0 | AE12: 0 | AF12: 0 | AG12: 0 | AH12: 1 | AI12: 190 | AJ12: 1 | AK12: 95 | AL12: 1 | AM12: 190 | AN12: 1 | AO12: 203 | AP12: 0 | AQ12: 0
A13: 45301 | B13: Wednesday | C13: Weekday | D13: 5 | E13: 1 | F13: 4 | G13: 2929 | H13: 1598 | I13: 1331 | J13: 232 | K13: 97 | L13: 806 | M13: 65 | N13: 40 | O13: =SUM(J13:N13) -> 1240 | P13: =G13-O13 -> 1689 | Q13: Hair Color / Cellophane Treatment | R13: Low (Post-Holiday) | T13: 0 | U13: 0 | V13: 0 | W13: 0 | X13: 0 | Y13: 0 | Z13: 0 | AA13: 0 | AB13: 1 | AC13: 1598 | AD13: 0 | AE13: 0 | AF13: 0 | AG13: 0 | AH13: 1 | AI13: 373 | AJ13: 1 | AK13: 186 | AL13: 1 | AM13: 373 | AN13: 1 | AO13: 399 | AP13: 0 | AQ13: 0
A14: 45302 | B14: Thursday | C14: Weekday | D14: 6 | E14: 2 | F14: 4 | G14: 3131 | H14: 2419 | I14: 712 | J14: 232 | K14: 97 | L14: 806 | M14: 69 | N14: 49 | O14: =SUM(J14:N14) -> 1253 | P14: =G14-O14 -> 1878 | Q14: Rebond, Cello, Haircut | R14: Low (Post-Holiday) | T14: 1 | U14: 1566 | V14: 0 | W14: 0 | X14: 0 | Y14: 0 | Z14: 0 | AA14: 0 | AB14: 1 | AC14: 854 | AD14: 0 | AE14: 0 | AF14: 0 | AG14: 0 | AH14: 1 | AI14: 199 | AJ14: 1 | AK14: 100 | AL14: 1 | AM14: 199 | AN14: 1 | AO14: 213 | AP14: 0 | AQ14: 0
A15: 45303 | B15: Friday | C15: Weekday | D15: 6 | E15: 1 | F15: 5 | G15: 3391 | H15: 2016 | I15: 1375 | J15: 232 | K15: 97 | L15: 806 | M15: 75 | N15: 49 | O15: =SUM(J15:N15) -> 1259 | P15: =G15-O15 -> 2132 | Q15: Rebond, Cello, Haircut | R15: Low (Post-Holiday) | T15: 1 | U15: 2016 | V15: 0 | W15: 0 | X15: 0 | Y15: 0 | Z15: 0 | AA15: 0 | AB15: 0 | AC15: 0 | AD15: 0 | AE15: 0 | AF15: 0 | AG15: 0 | AH15: 1 | AI15: 257 | AJ15: 1 | AK15: 128 | AL15: 1 | AM15: 257 | AN15: 1 | AO15: 275 | AP15: 1 | AQ15: 458
... A734: 46022 | B734: Wednesday | C734: Weekday | D734: 22 | E734: 11 | F734: 11 | G734: 11404 | H734: 7406 | I734: 3998 | J734: 290 | K734: 113 | L734: 806 | M734: 252 | N734: 178 | O734: =SUM(J734:N734) -> 1639 | P734: =G734-O734 -> 9765 | Q734: Rebond, Cello, Haircut | R734: Peak (Holiday) | T734: 2 | U734: 2314 | V734: 1 | W734: 1999 | X734: 1 | Y734: 1841 | Z734: 1 | AA734: 842 | AB734: 2 | AC734: 1262 | AD734: 1 | AE734: 1052 | AF734: 0 | AG734: 0 | AH734: 4 | AI734: 589 | AJ734: 3 | AK734: 221 | AL734: 3 | AM734: 442 | AN734: 2 | AO734: 316 | AP734: 2 | AQ734: 526

Sheet Monthly Trends
A1: MONTHLY TRENDS & MONTH-ON-MONTH (MoM) COMPARISON
A2: Arrows/colors compare each month vs. the prior month. 🟢 ▲ green = increase, 🔴 ▼ red = decrease. Peak/Low months are tagged per seasonal pattern (Dec/Mar-May = peak; Jun-Sep = low).
A3: Month | B3: Year | C3: Sessions | D3: Revenue (₱) | E3: Total Expenses (₱) | F3: Net Income (₱) | G3: Net Margin % | H3: Revenue MoM % | I3: Revenue MoM Trend | J3: Sessions MoM % | K3: Period Type
A4: January | B4: 2024 | C4: =SUMPRODUCT(('Daily Data'!$A$4:$A$734>=DATE(2024,1,1))*('Daily Data'!$A$4:$A$734<DATE(2024,2,1))*'Daily Data'!$D$4:$D$734) -> 179 | D4: =SUMPRODUCT(('Daily Data'!$A$4:$A$734>=DATE(2024,1,1))*('Daily Data'!$A$4:$A$734<DATE(2024,2,1))*'Daily Data'!$G$4:$G$734) -> 96327 | E4: =SUMPRODUCT(('Daily Data'!$A$4:$A$734>=DATE(2024,1,1))*('Daily Data'!$A$4:$A$734<DATE(2024,2,1))*'Daily Data'!$O$4:$O$734) -> 38764 | F4: =D4-E4 -> 57563 | G4: =IF(D4=0,0,F4/D4) -> 0.59757908 | H4: n/a | I4: — | J4: n/a | K4: Normal
A5: February | B5: 2024 | C5: =SUMPRODUCT(('Daily Data'!$A$4:$A$734>=DATE(2024,2,1))*('Daily Data'!$A$4:$A$734<DATE(2024,3,1))*'Daily Data'!$D$4:$D$734) -> 218 | D5: =SUMPRODUCT(('Daily Data'!$A$4:$A$734>=DATE(2024,2,1))*('Daily Data'!$A$4:$A$734<DATE(2024,3,1))*'Daily Data'!$G$4:$G$734) -> 116075 | E5: =SUMPRODUCT(('Daily Data'!$A$4:$A$734>=DATE(2024,2,1))*('Daily Data'!$A$4:$A$734<DATE(2024,3,1))*'Daily Data'!$O$4:$O$734) -> 39627 | F5: =D5-E5 -> 76448 | G5: =IF(D5=0,0,F5/D5) -> 0.65860866 | H5: =IF(D4=0,0,(D5-D4)/D4) -> 0.20501002 | I5: =IF(D5>=D4,"▲ Increase","▼ Decrease") -> ▲ Increase | J5: =IF(C4=0,0,(C5-C4)/C4) -> 0.21787709 | K5: Normal
A6: March | B6: 2024 | C6: =SUMPRODUCT(('Daily Data'!$A$4:$A$734>=DATE(2024,3,1))*('Daily Data'!$A$4:$A$734<DATE(2024,4,1))*'Daily Data'!$D$4:$D$734) -> 247 | D6: =SUMPRODUCT(('Daily Data'!$A$4:$A$734>=DATE(2024,3,1))*('Daily Data'!$A$4:$A$734<DATE(2024,4,1))*'Daily Data'!$G$4:$G$734) -> 132536 | E6: =SUMPRODUCT(('Daily Data'!$A$4:$A$734>=DATE(2024,3,1))*('Daily Data'!$A$4:$A$734<DATE(2024,4,1))*'Daily Data'!$O$4:$O$734) -> 40426 | F6: =D6-E6 -> 92110 | G6: =IF(D6=0,0,F6/D6) -> 0.69498099 | H6: =IF(D5=0,0,(D6-D5)/D5) -> 0.14181348 | I6: =IF(D6>=D5,"▲ Increase","▼ Decrease") -> ▲ Increase | J6: =IF(C5=0,0,(C6-C5)/C5) -> 0.13302752 | K6: Peak
A7: April | B7: 2024 | C7: =SUMPRODUCT(('Daily Data'!$A$4:$A$734>=DATE(2024,4,1))*('Daily Data'!$A$4:$A$734<DATE(2024,5,1))*'Daily Data'!$D$4:$D$734) -> 240 | D7: =SUMPRODUCT(('Daily Data'!$A$4:$A$734>=DATE(2024,4,1))*('Daily Data'!$A$4:$A$734<DATE(2024,5,1))*'Daily Data'!$G$4:$G$734) -> 127508 | E7: =SUMPRODUCT(('Daily Data'!$A$4:$A$734>=DATE(2024,4,1))*('Daily Data'!$A$4:$A$734<DATE(2024,5,1))*'Daily Data'!$O$4:$O$734) -> 40552 | F7: =D7-E7 -> 86956 | G7: =IF(D7=0,0,F7/D7) -> 0.68196505 | H7: =IF(D6=0,0,(D7-D6)/D6) -> -0.037936862 | I7: =IF(D7>=D6,"▲ Increase","▼ Decrease") -> ▼ Decrease | J7: =IF(C6=0,0,(C7-C6)/C6) -> -0.028340081 | K7: Peak
A8: May | B8: 2024 | C8: =SUMPRODUCT(('Daily Data'!$A$4:$A$734>=DATE(2024,5,1))*('Daily Data'!$A$4:$A$734<DATE(2024,6,1))*'Daily Data'!$D$4:$D$734) -> 274 | D8: =SUMPRODUCT(('Daily Data'!$A$4:$A$734>=DATE(2024,5,1))*('Daily Data'!$A$4:$A$734<DATE(2024,6,1))*'Daily Data'!$G$4:$G$734) -> 145616 | E8: =SUMPRODUCT(('Daily Data'!$A$4:$A$734>=DATE(2024,5,1))*('Daily Data'!$A$4:$A$734<DATE(2024,6,1))*'Daily Data'!$O$4:$O$734) -> 41300 | F8: =D8-E8 -> 104316 | G8: =IF(D8=0,0,F8/D8) -> 0.71637732 | H8: =IF(D7=0,0,(D8-D7)/D7) -> 0.14201462 | I8: =IF(D8>=D7,"▲ Increase","▼ Decrease") -> ▲ Increase | J8: =IF(C7=0,0,(C8-C7)/C7) -> 0.14166667 | K8: Peak
A9: June | B9: 2024 | C9: =SUMPRODUCT(('Daily Data'!$A$4:$A$734>=DATE(2024,6,1))*('Daily Data'!$A$4:$A$734<DATE(2024,7,1))*'Daily Data'!$D$4:$D$734) -> 201 | D9: =SUMPRODUCT(('Daily Data'!$A$4:$A$734>=DATE(2024,6,1))*('Daily Data'!$A$4:$A$734<DATE(2024,7,1))*'Daily Data'!$G$4:$G$734) -> 106279 | E9: =SUMPRODUCT(('Daily Data'!$A$4:$A$734>=DATE(2024,6,1))*('Daily Data'!$A$4:$A$734<DATE(2024,7,1))*'Daily Data'!$O$4:$O$734) -> 39472 | F9: =D9-E9 -> 66807 | G9: =IF(D9=0,0,F9/D9) -> 0.62860019 | H9: =IF(D8=0,0,(D9-D8)/D8) -> -0.27014202 | I9: =IF(D9>=D8,"▲ Increase","▼ Decrease") -> ▼ Decrease | J9: =IF(C8=0,0,(C9-C8)/C8) -> -0.26642336 | K9: Low
A10: July | B10: 2024 | C10: =SUMPRODUCT(('Daily Data'!$A$4:$A$734>=DATE(2024,7,1))*('Daily Data'!$A$4:$A$734<DATE(2024,8,1))*'Daily Data'!$D$4:$D$734) -> 181 | D10: =SUMPRODUCT(('Daily Data'!$A$4:$A$734>=DATE(2024,7,1))*('Daily Data'!$A$4:$A$734<DATE(2024,8,1))*'Daily Data'!$G$4:$G$734) -> 96561 | E10: =SUMPRODUCT(('Daily Data'!$A$4:$A$734>=DATE(2024,7,1))*('Daily Data'!$A$4:$A$734<DATE(2024,8,1))*'Daily Data'!$O$4:$O$734) -> 38778 | F10: =D10-E10 -> 57783 | G10: =IF(D10=0,0,F10/D10) -> 0.5984093 | H10: =IF(D9=0,0,(D10-D9)/D9) -> -0.091438572 | I10: =IF(D10>=D9,"▲ Increase","▼ Decrease") -> ▼ Decrease | J10: =IF(C9=0,0,(C10-C9)/C9) -> -0.099502488 | K10: Low
A11: August | B11: 2024 | C11: =SUMPRODUCT(('Daily Data'!$A$4:$A$734>=DATE(2024,8,1))*('Daily Data'!$A$4:$A$734<DATE(2024,9,1))*'Daily Data'!$D$4:$D$734) -> 192 | D11: =SUMPRODUCT(('Daily Data'!$A$4:$A$734>=DATE(2024,8,1))*('Daily Data'!$A$4:$A$734<DATE(2024,9,1))*'Daily Data'!$G$4:$G$734) -> 101935 | E11: =SUMPRODUCT(('Daily Data'!$A$4:$A$734>=DATE(2024,8,1))*('Daily Data'!$A$4:$A$734<DATE(2024,9,1))*'Daily Data'!$O$4:$O$734) -> 38992 | F11: =D11-E11 -> 62943 | G11: =IF(D11=0,0,F11/D11) -> 0.61748173 | H11: =IF(D10=0,0,(D11-D10)/D10) -> 0.055653939 | I11: =IF(D11>=D10,"▲ Increase","▼ Decrease") -> ▲ Increase | J11: =IF(C10=0,0,(C11-C10)/C10) -> 0.060773481 | K11: Low
A12: September | B12: 2024 | C12: =SUMPRODUCT(('Daily Data'!$A$4:$A$734>=DATE(2024,9,1))*('Daily Data'!$A$4:$A$734<DATE(2024,10,1))*'Daily Data'!$D$4:$D$734) -> 191 | D12: =SUMPRODUCT(('Daily Data'!$A$4:$A$734>=DATE(2024,9,1))*('Daily Data'!$A$4:$A$734<DATE(2024,10,1))*'Daily Data'!$G$4:$G$734) -> 102291 | E12: =SUMPRODUCT(('Daily Data'!$A$4:$A$734>=DATE(2024,9,1))*('Daily Data'!$A$4:$A$734<DATE(2024,10,1))*'Daily Data'!$O$4:$O$734) -> 39000 | F12: =D12-E12 -> 63291 | G12: =IF(D12=0,0,F12/D12) -> 0.61873479 | H12: =IF(D11=0,0,(D12-D11)/D11) -> 0.0034924216 | I12: =IF(D12>=D11,"▲ Increase","▼ Decrease") -> ▲ Increase | J12: =IF(C11=0,0,(C12-C11)/C11) -> -0.0052083333 | K12: Low
A13: October | B13: 2024 | C13: =SUMPRODUCT(('Daily Data'!$A$4:$A$734>=DATE(2024,10,1))*('Daily Data'!$A$4:$A$734<DATE(2024,11,1))*'Daily Data'!$D$4:$D$734) -> 222 | D13: =SUMPRODUCT(('Daily Data'!$A$4:$A$734>=DATE(2024,10,1))*('Daily Data'!$A$4:$A$734<DATE(2024,11,1))*'Daily Data'!$G$4:$G$734) -> 119752 | E13: =SUMPRODUCT(('Daily Data'!$A$4:$A$734>=DATE(2024,10,1))*('Daily Data'!$A$4:$A$734<DATE(2024,11,1))*'Daily Data'!$O$4:$O$734) -> 39727 | F13: =D13-E13 -> 80025 | G13: =IF(D13=0,0,F13/D13) -> 0.66825606 | H13: =IF(D12=0,0,(D13-D12)/D12) -> 0.17069928 | I13: =IF(D13>=D12,"▲ Increase","▼ Decrease") -> ▲ Increase | J13: =IF(C12=0,0,(C13-C12)/C12) -> 0.16230366 | K13: Normal
A14: November | B14: 2024 | C14: =SUMPRODUCT(('Daily Data'!$A$4:$A$734>=DATE(2024,11,1))*('Daily Data'!$A$4:$A$734<DATE(2024,12,1))*'Daily Data'!$D$4:$D$734) -> 230 | D14: =SUMPRODUCT(('Daily Data'!$A$4:$A$734>=DATE(2024,11,1))*('Daily Data'!$A$4:$A$734<DATE(2024,12,1))*'Daily Data'!$G$4:$G$734) -> 122428 | E14: =SUMPRODUCT(('Daily Data'!$A$4:$A$734>=DATE(2024,11,1))*('Daily Data'!$A$4:$A$734<DATE(2024,12,1))*'Daily Data'!$O$4:$O$734) -> 40059 | F14: =D14-E14 -> 82369 | G14: =IF(D14=0,0,F14/D14) -> 0.67279544 | H14: =IF(D13=0,0,(D14-D13)/D13) -> 0.022346182 | I14: =IF(D14>=D13,"▲ Increase","▼ Decrease") -> ▲ Increase | J14: =IF(C13=0,0,(C14-C13)/C13) -> 0.036036036 | K14: Normal
A15: December | B15: 2024 | C15: =SUMPRODUCT(('Daily Data'!$A$4:$A$734>=DATE(2024,12,1))*('Daily Data'!$A$4:$A$734<DATE(2025,1,1))*'Daily Data'!$D$4:$D$734) -> 512 | D15: =SUMPRODUCT(('Daily Data'!$A$4:$A$734>=DATE(2024,12,1))*('Daily Data'!$A$4:$A$734<DATE(2025,1,1))*'Daily Data'!$G$4:$G$734) -> 271882 | E15: =SUMPRODUCT(('Daily Data'!$A$4:$A$734>=DATE(2024,12,1))*('Daily Data'!$A$4:$A$734<DATE(2025,1,1))*'Daily Data'!$O$4:$O$734) -> 47621 | F15: =D15-E15 -> 224261 | G15: =IF(D15=0,0,F15/D15) -> 0.82484681 | H15: =IF(D14=0,0,(D15-D14)/D14) -> 1.2207502 | I15: =IF(D15>=D14,"▲ Increase","▼ Decrease") -> ▲ Increase | J15: =IF(C14=0,0,(C15-C14)/C14) -> 1.226087 | K15: Peak
A16: January | B16: 2025 | C16: =SUMPRODUCT(('Daily Data'!$A$4:$A$734>=DATE(2025,1,1))*('Daily Data'!$A$4:$A$734<DATE(2025,2,1))*'Daily Data'!$D$4:$D$734) -> 181 | D16: =SUMPRODUCT(('Daily Data'!$A$4:$A$734>=DATE(2025,1,1))*('Daily Data'!$A$4:$A$734<DATE(2025,2,1))*'Daily Data'!$G$4:$G$734) -> 96490 | E16: =SUMPRODUCT(('Daily Data'!$A$4:$A$734>=DATE(2025,1,1))*('Daily Data'!$A$4:$A$734<DATE(2025,2,1))*'Daily Data'!$O$4:$O$734) -> 38778 | F16: =D16-E16 -> 57712 | G16: =IF(D16=0,0,F16/D16) -> 0.59811379 | H16: =IF(D15=0,0,(D16-D15)/D15) -> -0.64510339 | I16: =IF(D16>=D15,"▲ Increase","▼ Decrease") -> ▼ Decrease | J16: =IF(C15=0,0,(C16-C15)/C15) -> -0.64648438 | K16: Normal
A17: February | B17: 2025 | C17: =SUMPRODUCT(('Daily Data'!$A$4:$A$734>=DATE(2025,2,1))*('Daily Data'!$A$4:$A$734<DATE(2025,3,1))*'Daily Data'!$D$4:$D$734) -> 217 | D17: =SUMPRODUCT(('Daily Data'!$A$4:$A$734>=DATE(2025,2,1))*('Daily Data'!$A$4:$A$734<DATE(2025,3,1))*'Daily Data'!$G$4:$G$734) -> 115730 | E17: =SUMPRODUCT(('Daily Data'!$A$4:$A$734>=DATE(2025,2,1))*('Daily Data'!$A$4:$A$734<DATE(2025,3,1))*'Daily Data'!$O$4:$O$734) -> 39624 | F17: =D17-E17 -> 76106 | G17: =IF(D17=0,0,F17/D17) -> 0.65761687 | H17: =IF(D16=0,0,(D17-D16)/D16) -> 0.1993989 | I17: =IF(D17>=D16,"▲ Increase","▼ Decrease") -> ▲ Increase | J17: =IF(C16=0,0,(C17-C16)/C16) -> 0.19889503 | K17: Normal
A18: March | B18: 2025 | C18: =SUMPRODUCT(('Daily Data'!$A$4:$A$734>=DATE(2025,3,1))*('Daily Data'!$A$4:$A$734<DATE(2025,4,1))*'Daily Data'!$D$4:$D$734) -> 238 | D18: =SUMPRODUCT(('Daily Data'!$A$4:$A$734>=DATE(2025,3,1))*('Daily Data'!$A$4:$A$734<DATE(2025,4,1))*'Daily Data'!$G$4:$G$734) -> 124840 | E18: =SUMPRODUCT(('Daily Data'!$A$4:$A$734>=DATE(2025,3,1))*('Daily Data'!$A$4:$A$734<DATE(2025,4,1))*'Daily Data'!$O$4:$O$734) -> 40182 | F18: =D18-E18 -> 84658 | G18: =IF(D18=0,0,F18/D18) -> 0.67813201 | H18: =IF(D17=0,0,(D18-D17)/D17) -> 0.078717705 | I18: =IF(D18>=D17,"▲ Increase","▼ Decrease") -> ▲ Increase | J18: =IF(C17=0,0,(C18-C17)/C17) -> 0.096774194 | K18: Peak
A19: April | B19: 2025 | C19: =SUMPRODUCT(('Daily Data'!$A$4:$A$734>=DATE(2025,4,1))*('Daily Data'!$A$4:$A$734<DATE(2025,5,1))*'Daily Data'!$D$4:$D$734) -> 208 | D19: =SUMPRODUCT(('Daily Data'!$A$4:$A$734>=DATE(2025,4,1))*('Daily Data'!$A$4:$A$734<DATE(2025,5,1))*'Daily Data'!$G$4:$G$734) -> 109480 | E19: =SUMPRODUCT(('Daily Data'!$A$4:$A$734>=DATE(2025,4,1))*('Daily Data'!$A$4:$A$734<DATE(2025,5,1))*'Daily Data'!$O$4:$O$734) -> 39896 | F19: =D19-E19 -> 69584 | G19: =IF(D19=0,0,F19/D19) -> 0.63558641 | H19: =IF(D18=0,0,(D19-D18)/D18) -> -0.12303749 | I19: =IF(D19>=D18,"▲ Increase","▼ Decrease") -> ▼ Decrease | J19: =IF(C18=0,0,(C19-C18)/C18) -> -0.12605042 | K19: Peak
A20: May | B20: 2025 | C20: =SUMPRODUCT(('Daily Data'!$A$4:$A$734>=DATE(2025,5,1))*('Daily Data'!$A$4:$A$734<DATE(2025,6,1))*'Daily Data'!$D$4:$D$734) -> 238 | D20: =SUMPRODUCT(('Daily Data'!$A$4:$A$734>=DATE(2025,5,1))*('Daily Data'!$A$4:$A$734<DATE(2025,6,1))*'Daily Data'!$G$4:$G$734) -> 124601 | E20: =SUMPRODUCT(('Daily Data'!$A$4:$A$734>=DATE(2025,5,1))*('Daily Data'!$A$4:$A$734<DATE(2025,6,1))*'Daily Data'!$O$4:$O$734) -> 40550 | F20: =D20-E20 -> 84051 | G20: =IF(D20=0,0,F20/D20) -> 0.6745612 | H20: =IF(D19=0,0,(D20-D19)/D19) -> 0.13811655 | I20: =IF(D20>=D19,"▲ Increase","▼ Decrease") -> ▲ Increase | J20: =IF(C19=0,0,(C20-C19)/C19) -> 0.14423077 | K20: Peak
A21: June | B21: 2025 | C21: =SUMPRODUCT(('Daily Data'!$A$4:$A$734>=DATE(2025,6,1))*('Daily Data'!$A$4:$A$734<DATE(2025,7,1))*'Daily Data'!$D$4:$D$734) -> 199 | D21: =SUMPRODUCT(('Daily Data'!$A$4:$A$734>=DATE(2025,6,1))*('Daily Data'!$A$4:$A$734<DATE(2025,7,1))*'Daily Data'!$G$4:$G$734) -> 106321 | E21: =SUMPRODUCT(('Daily Data'!$A$4:$A$734>=DATE(2025,6,1))*('Daily Data'!$A$4:$A$734<DATE(2025,7,1))*'Daily Data'!$O$4:$O$734) -> 39458 | F21: =D21-E21 -> 66863 | G21: =IF(D21=0,0,F21/D21) -> 0.62887858 | H21: =IF(D20=0,0,(D21-D20)/D20) -> -0.14670829 | I21: =IF(D21>=D20,"▲ Increase","▼ Decrease") -> ▼ Decrease | J21: =IF(C20=0,0,(C21-C20)/C20) -> -0.16386555 | K21: Low
A22: July | B22: 2025 | C22: =SUMPRODUCT(('Daily Data'!$A$4:$A$734>=DATE(2025,7,1))*('Daily Data'!$A$4:$A$734<DATE(2025,8,1))*'Daily Data'!$D$4:$D$734) -> 192 | D22: =SUMPRODUCT(('Daily Data'!$A$4:$A$734>=DATE(2025,7,1))*('Daily Data'!$A$4:$A$734<DATE(2025,8,1))*'Daily Data'!$G$4:$G$734) -> 101003 | E22: =SUMPRODUCT(('Daily Data'!$A$4:$A$734>=DATE(2025,7,1))*('Daily Data'!$A$4:$A$734<DATE(2025,8,1))*'Daily Data'!$O$4:$O$734) -> 38975 | F22: =D22-E22 -> 62028 | G22: =IF(D22=0,0,F22/D22) -> 0.61412037 | H22: =IF(D21=0,0,(D22-D21)/D21) -> -0.050018341 | I22: =IF(D22>=D21,"▲ Increase","▼ Decrease") -> ▼ Decrease | J22: =IF(C21=0,0,(C22-C21)/C21) -> -0.035175879 | K22: Low
A23: August | B23: 2025 | C23: =SUMPRODUCT(('Daily Data'!$A$4:$A$734>=DATE(2025,8,1))*('Daily Data'!$A$4:$A$734<DATE(2025,9,1))*'Daily Data'!$D$4:$D$734) -> 199 | D23: =SUMPRODUCT(('Daily Data'!$A$4:$A$734>=DATE(2025,8,1))*('Daily Data'!$A$4:$A$734<DATE(2025,9,1))*'Daily Data'!$G$4:$G$734) -> 103945 | E23: =SUMPRODUCT(('Daily Data'!$A$4:$A$734>=DATE(2025,8,1))*('Daily Data'!$A$4:$A$734<DATE(2025,9,1))*'Daily Data'!$O$4:$O$734) -> 39099 | F23: =D23-E23 -> 64846 | G23: =IF(D23=0,0,F23/D23) -> 0.62384915 | H23: =IF(D22=0,0,(D23-D22)/D22) -> 0.029127848 | I23: =IF(D23>=D22,"▲ Increase","▼ Decrease") -> ▲ Increase | J23: =IF(C22=0,0,(C23-C22)/C22) -> 0.036458333 | K23: Low
A24: September | B24: 2025 | C24: =SUMPRODUCT(('Daily Data'!$A$4:$A$734>=DATE(2025,9,1))*('Daily Data'!$A$4:$A$734<DATE(2025,10,1))*'Daily Data'!$D$4:$D$734) -> 198 | D24: =SUMPRODUCT(('Daily Data'!$A$4:$A$734>=DATE(2025,9,1))*('Daily Data'!$A$4:$A$734<DATE(2025,10,1))*'Daily Data'!$G$4:$G$734) -> 105360 | E24: =SUMPRODUCT(('Daily Data'!$A$4:$A$734>=DATE(2025,9,1))*('Daily Data'!$A$4:$A$734<DATE(2025,10,1))*'Daily Data'!$O$4:$O$734) -> 39127 | F24: =D24-E24 -> 66233 | G24: =IF(D24=0,0,F24/D24) -> 0.62863516 | H24: =IF(D23=0,0,(D24-D23)/D23) -> 0.013612968 | I24: =IF(D24>=D23,"▲ Increase","▼ Decrease") -> ▲ Increase | J24: =IF(C23=0,0,(C24-C23)/C23) -> -0.0050251256 | K24: Low
A25: October | B25: 2025 | C25: =SUMPRODUCT(('Daily Data'!$A$4:$A$734>=DATE(2025,10,1))*('Daily Data'!$A$4:$A$734<DATE(2025,11,1))*'Daily Data'!$D$4:$D$734) -> 234 | D25: =SUMPRODUCT(('Daily Data'!$A$4:$A$734>=DATE(2025,10,1))*('Daily Data'!$A$4:$A$734<DATE(2025,11,1))*'Daily Data'!$G$4:$G$734) -> 123061 | E25: =SUMPRODUCT(('Daily Data'!$A$4:$A$734>=DATE(2025,10,1))*('Daily Data'!$A$4:$A$734<DATE(2025,11,1))*'Daily Data'!$O$4:$O$734) -> 39897 | F25: =D25-E25 -> 83164 | G25: =IF(D25=0,0,F25/D25) -> 0.67579493 | H25: =IF(D24=0,0,(D25-D24)/D24) -> 0.16800494 | I25: =IF(D25>=D24,"▲ Increase","▼ Decrease") -> ▲ Increase | J25: =IF(C24=0,0,(C25-C24)/C24) -> 0.18181818 | K25: Normal
A26: November | B26: 2025 | C26: =SUMPRODUCT(('Daily Data'!$A$4:$A$734>=DATE(2025,11,1))*('Daily Data'!$A$4:$A$734<DATE(2025,12,1))*'Daily Data'!$D$4:$D$734) -> 242 | D26: =SUMPRODUCT(('Daily Data'!$A$4:$A$734>=DATE(2025,11,1))*('Daily Data'!$A$4:$A$734<DATE(2025,12,1))*'Daily Data'!$G$4:$G$734) -> 127832 | E26: =SUMPRODUCT(('Daily Data'!$A$4:$A$734>=DATE(2025,11,1))*('Daily Data'!$A$4:$A$734<DATE(2025,12,1))*'Daily Data'!$O$4:$O$734) -> 40276 | F26: =D26-E26 -> 87556 | G26: =IF(D26=0,0,F26/D26) -> 0.68493022 | H26: =IF(D25=0,0,(D26-D25)/D25) -> 0.038769391 | I26: =IF(D26>=D25,"▲ Increase","▼ Decrease") -> ▲ Increase | J26: =IF(C25=0,0,(C26-C25)/C25) -> 0.034188034 | K26: Normal
A27: December | B27: 2025 | C27: =SUMPRODUCT(('Daily Data'!$A$4:$A$734>=DATE(2025,12,1))*('Daily Data'!$A$4:$A$734<DATE(2026,1,1))*'Daily Data'!$D$4:$D$734) -> 518 | D27: =SUMPRODUCT(('Daily Data'!$A$4:$A$734>=DATE(2025,12,1))*('Daily Data'!$A$4:$A$734<DATE(2026,1,1))*'Daily Data'!$G$4:$G$734) -> 275623 | E27: =SUMPRODUCT(('Daily Data'!$A$4:$A$734>=DATE(2025,12,1))*('Daily Data'!$A$4:$A$734<DATE(2026,1,1))*'Daily Data'!$O$4:$O$734) -> 47752 | F27: =D27-E27 -> 227871 | G27: =IF(D27=0,0,F27/D27) -> 0.82674886 | H27: =IF(D26=0,0,(D27-D26)/D26) -> 1.1561346 | I27: =IF(D27>=D26,"▲ Increase","▼ Decrease") -> ▲ Increase | J27: =IF(C26=0,0,(C27-C26)/C26) -> 1.1404959 | K27: Peak
A28: TOTAL / AVERAGE | C28: =SUM(C4:C27) -> 5751 | D28: =SUM(D4:D27) -> 3053476 | E28: =SUM(E4:E27) -> 967932 | F28: =SUM(F4:F27) -> 2085544 | G28: =F28/D28 -> 0.68300651

Sheet Weekly Trends
A1: WEEKLY TRENDS (ISO WEEKS, JAN 2024 – DEC 2025)
A2: Each row = one calendar week (Mon-Sun). Trend column compares revenue vs. prior week. 🟢▲=increase, 🔴▼=decrease.
A3: Week # | B3: Week Start | C3: Week End | D3: Sessions | E3: Revenue (₱) | F3: Net Income (₱) | G3: Revenue WoW % | H3: Trend | I3: Tag
A4: 1 | B4: 45292 | C4: 45298 | D4: =SUMPRODUCT(('Daily Data'!$A$4:$A$734>=B4)*('Daily Data'!$A$4:$A$734<=C4)*'Daily Data'!$D$4:$D$734) -> 38 | E4: =SUMPRODUCT(('Daily Data'!$A$4:$A$734>=B4)*('Daily Data'!$A$4:$A$734<=C4)*'Daily Data'!$G$4:$G$734) -> 19707 | F4: =SUMPRODUCT(('Daily Data'!$A$4:$A$734>=B4)*('Daily Data'!$A$4:$A$734<=C4)*'Daily Data'!$P$4:$P$734) -> 11017 | G4: n/a | H4: — | I4: Normal
A5: 2 | B5: 45299 | C5: 45305 | D5: =SUMPRODUCT(('Daily Data'!$A$4:$A$734>=B5)*('Daily Data'!$A$4:$A$734<=C5)*'Daily Data'!$D$4:$D$734) -> 42 | E5: =SUMPRODUCT(('Daily Data'!$A$4:$A$734>=B5)*('Daily Data'!$A$4:$A$734<=C5)*'Daily Data'!$G$4:$G$734) -> 22717 | F5: =SUMPRODUCT(('Daily Data'!$A$4:$A$734>=B5)*('Daily Data'!$A$4:$A$734<=C5)*'Daily Data'!$P$4:$P$734) -> 13929 | G5: =IF(E4=0,0,(E5-E4)/E4) -> 0.15273761 | H5: =IF(E5>=E4,"▲ Increase","▼ Decrease") -> ▲ Increase | I5: Normal
A6: 3 | B6: 45306 | C6: 45312 | D6: =SUMPRODUCT(('Daily Data'!$A$4:$A$734>=B6)*('Daily Data'!$A$4:$A$734<=C6)*'Daily Data'!$D$4:$D$734) -> 44 | E6: =SUMPRODUCT(('Daily Data'!$A$4:$A$734>=B6)*('Daily Data'!$A$4:$A$734<=C6)*'Daily Data'!$G$4:$G$734) -> 23329 | F6: =SUMPRODUCT(('Daily Data'!$A$4:$A$734>=B6)*('Daily Data'!$A$4:$A$734<=C6)*'Daily Data'!$P$4:$P$734) -> 14511 | G6: =IF(E5=0,0,(E6-E5)/E5) -> 0.026940177 | H6: =IF(E6>=E5,"▲ Increase","▼ Decrease") -> ▲ Increase | I6: Normal
A7: 4 | B7: 45313 | C7: 45319 | D7: =SUMPRODUCT(('Daily Data'!$A$4:$A$734>=B7)*('Daily Data'!$A$4:$A$734<=C7)*'Daily Data'!$D$4:$D$734) -> 40 | E7: =SUMPRODUCT(('Daily Data'!$A$4:$A$734>=B7)*('Daily Data'!$A$4:$A$734<=C7)*'Daily Data'!$G$4:$G$734) -> 22025 | F7: =SUMPRODUCT(('Daily Data'!$A$4:$A$734>=B7)*('Daily Data'!$A$4:$A$734<=C7)*'Daily Data'!$P$4:$P$734) -> 13270 | G7: =IF(E6=0,0,(E7-E6)/E6) -> -0.055896095 | H7: =IF(E7>=E6,"▲ Increase","▼ Decrease") -> ▼ Decrease | I7: Normal
A8: 5 | B8: 45320 | C8: 45326 | D8: =SUMPRODUCT(('Daily Data'!$A$4:$A$734>=B8)*('Daily Data'!$A$4:$A$734<=C8)*'Daily Data'!$D$4:$D$734) -> 48 | E8: =SUMPRODUCT(('Daily Data'!$A$4:$A$734>=B8)*('Daily Data'!$A$4:$A$734<=C8)*'Daily Data'!$G$4:$G$734) -> 25923 | F8: =SUMPRODUCT(('Daily Data'!$A$4:$A$734>=B8)*('Daily Data'!$A$4:$A$734<=C8)*'Daily Data'!$P$4:$P$734) -> 16690 | G8: =IF(E7=0,0,(E8-E7)/E7) -> 0.1769807 | H8: =IF(E8>=E7,"▲ Increase","▼ Decrease") -> ▲ Increase | I8: Normal
A9: 6 | B9: 45327 | C9: 45333 | D9: =SUMPRODUCT(('Daily Data'!$A$4:$A$734>=B9)*('Daily Data'!$A$4:$A$734<=C9)*'Daily Data'!$D$4:$D$734) -> 52 | E9: =SUMPRODUCT(('Daily Data'!$A$4:$A$734>=B9)*('Daily Data'!$A$4:$A$734<=C9)*'Daily Data'!$G$4:$G$734) -> 27552 | F9: =SUMPRODUCT(('Daily Data'!$A$4:$A$734>=B9)*('Daily Data'!$A$4:$A$734<=C9)*'Daily Data'!$P$4:$P$734) -> 18002 | G9: =IF(E8=0,0,(E9-E8)/E8) -> 0.062839949 | H9: =IF(E9>=E8,"▲ Increase","▼ Decrease") -> ▲ Increase | I9: Normal
A10: 7 | B10: 45334 | C10: 45340 | D10: =SUMPRODUCT(('Daily Data'!$A$4:$A$734>=B10)*('Daily Data'!$A$4:$A$734<=C10)*'Daily Data'!$D$4:$D$734) -> 54 | E10: =SUMPRODUCT(('Daily Data'!$A$4:$A$734>=B10)*('Daily Data'!$A$4:$A$734<=C10)*'Daily Data'!$G$4:$G$734) -> 28792 | F10: =SUMPRODUCT(('Daily Data'!$A$4:$A$734>=B10)*('Daily Data'!$A$4:$A$734<=C10)*'Daily Data'!$P$4:$P$734) -> 19200 | G10: =IF(E9=0,0,(E10-E9)/E9) -> 0.045005807 | H10: =IF(E10>=E9,"▲ Increase","▼ Decrease") -> ▲ Increase | I10: Normal
A11: 8 | B11: 45341 | C11: 45347 | D11: =SUMPRODUCT(('Daily Data'!$A$4:$A$734>=B11)*('Daily Data'!$A$4:$A$734<=C11)*'Daily Data'!$D$4:$D$734) -> 51 | E11: =SUMPRODUCT(('Daily Data'!$A$4:$A$734>=B11)*('Daily Data'!$A$4:$A$734<=C11)*'Daily Data'!$G$4:$G$734) -> 27738 | F11: =SUMPRODUCT(('Daily Data'!$A$4:$A$734>=B11)*('Daily Data'!$A$4:$A$734<=C11)*'Daily Data'!$P$4:$P$734) -> 18191 | G11: =IF(E10=0,0,(E11-E10)/E10) -> -0.036607391 | H11: =IF(E11>=E10,"▲ Increase","▼ Decrease") -> ▼ Decrease | I11: Normal
A12: 9 | B12: 45348 | C12: 45354 | D12: =SUMPRODUCT(('Daily Data'!$A$4:$A$734>=B12)*('Daily Data'!$A$4:$A$734<=C12)*'Daily Data'!$D$4:$D$734) -> 55 | E12: =SUMPRODUCT(('Daily Data'!$A$4:$A$734>=B12)*('Daily Data'!$A$4:$A$734<=C12)*'Daily Data'!$G$4:$G$734) -> 29323 | F12: =SUMPRODUCT(('Daily Data'!$A$4:$A$734>=B12)*('Daily Data'!$A$4:$A$734<=C12)*'Daily Data'!$P$4:$P$734) -> 19928 | G12: =IF(E11=0,0,(E12-E11)/E11) -> 0.057141827 | H12: =IF(E12>=E11,"▲ Increase","▼ Decrease") -> ▲ Increase | I12: Normal
A13: 10 | B13: 45355 | C13: 45361 | D13: =SUMPRODUCT(('Daily Data'!$A$4:$A$734>=B13)*('Daily Data'!$A$4:$A$734<=C13)*'Daily Data'!$D$4:$D$734) -> 54 | E13: =SUMPRODUCT(('Daily Data'!$A$4:$A$734>=B13)*('Daily Data'!$A$4:$A$734<=C13)*'Daily Data'!$G$4:$G$734) -> 29280 | F13: =SUMPRODUCT(('Daily Data'!$A$4:$A$734>=B13)*('Daily Data'!$A$4:$A$734<=C13)*'Daily Data'!$P$4:$P$734) -> 20180 | G13: =IF(E12=0,0,(E13-E12)/E12) -> -0.0014664257 | H13: =IF(E13>=E12,"▲ Increase","▼ Decrease") -> ▼ Decrease | I13: Peak
A14: 11 | B14: 45362 | C14: 45368 | D14: =SUMPRODUCT(('Daily Data'!$A$4:$A$734>=B14)*('Daily Data'!$A$4:$A$734<=C14)*'Daily Data'!$D$4:$D$734) -> 56 | E14: =SUMPRODUCT(('Daily Data'!$A$4:$A$734>=B14)*('Daily Data'!$A$4:$A$734<=C14)*'Daily Data'!$G$4:$G$734) -> 29924 | F14: =SUMPRODUCT(('Daily Data'!$A$4:$A$734>=B14)*('Daily Data'!$A$4:$A$734<=C14)*'Daily Data'!$P$4:$P$734) -> 20793 | G14: =IF(E13=0,0,(E14-E13)/E13) -> 0.021994536 | H14: =IF(E14>=E13,"▲ Increase","▼ Decrease") -> ▲ Increase | I14: Peak
A15: 12 | B15: 45369 | C15: 45375 | D15: =SUMPRODUCT(('Daily Data'!$A$4:$A$734>=B15)*('Daily Data'!$A$4:$A$734<=C15)*'Daily Data'!$D$4:$D$734) -> 54 | E15: =SUMPRODUCT(('Daily Data'!$A$4:$A$734>=B15)*('Daily Data'!$A$4:$A$734<=C15)*'Daily Data'!$G$4:$G$734) -> 29081 | F15: =SUMPRODUCT(('Daily Data'!$A$4:$A$734>=B15)*('Daily Data'!$A$4:$A$734<=C15)*'Daily Data'!$P$4:$P$734) -> 19986 | G15: =IF(E14=0,0,(E15-E14)/E14) -> -0.028171367 | H15: =IF(E15>=E14,"▲ Increase","▼ Decrease") -> ▼ Decrease | I15: Peak
A16: 13 | B16: 45376 | C16: 45382 | D16: =SUMPRODUCT(('Daily Data'!$A$4:$A$734>=B16)*('Daily Data'!$A$4:$A$734<=C16)*'Daily Data'!$D$4:$D$734) -> 56 | E16: =SUMPRODUCT(('Daily Data'!$A$4:$A$734>=B16)*('Daily Data'!$A$4:$A$734<=C16)*'Daily Data'!$G$4:$G$734) -> 29547 | F16: =SUMPRODUCT(('Daily Data'!$A$4:$A$734>=B16)*('Daily Data'!$A$4:$A$734<=C16)*'Daily Data'!$P$4:$P$734) -> 20424 | G16: =IF(E15=0,0,(E16-E15)/E15) -> 0.016024208 | H16: =IF(E16>=E15,"▲ Increase","▼ Decrease") -> ▲ Increase | I16: Peak
... A108: 105 | B108: 46020 | C108: 46022 | D108: =SUMPRODUCT(('Daily Data'!$A$4:$A$734>=B108)*('Daily Data'!$A$4:$A$734<=C108)*'Daily Data'!$D$4:$D$734) -> 59 | E108: =SUMPRODUCT(('Daily Data'!$A$4:$A$734>=B108)*('Daily Data'!$A$4:$A$734<=C108)*'Daily Data'!$G$4:$G$734) -> 31625 | F108: =SUMPRODUCT(('Daily Data'!$A$4:$A$734>=B108)*('Daily Data'!$A$4:$A$734<=C108)*'Daily Data'!$P$4:$P$734) -> 26822 | G108: =IF(E107=0,0,(E108-E107)/E107) -> -0.59542268 | H108: =IF(E108>=E107,"▲ Increase","▼ Decrease") -> ▼ Decrease | I108: Normal

Sheet Quarterly Trends
A1: QUARTERLY TRENDS & QoQ COMPARISON
A2: Q1=Jan-Mar (summer start), Q2=Apr-Jun (summer/rainy transition), Q3=Jul-Sep (rainy/low), Q4=Oct-Dec (peak holiday). Trend vs prior quarter.
A3: Quarter | B3: Year | C3: Sessions | D3: Revenue (₱) | E3: Net Income (₱) | F3: Net Margin % | G3: Revenue QoQ % | H3: Trend
A4: Q1 | B4: 2024 | C4: =SUMPRODUCT(('Daily Data'!$A$4:$A$734>=DATE(2024,1,1))*('Daily Data'!$A$4:$A$734<DATE(2024,4,1))*'Daily Data'!$D$4:$D$734) -> 644 | D4: =SUMPRODUCT(('Daily Data'!$A$4:$A$734>=DATE(2024,1,1))*('Daily Data'!$A$4:$A$734<DATE(2024,4,1))*'Daily Data'!$G$4:$G$734) -> 344938 | E4: =SUMPRODUCT(('Daily Data'!$A$4:$A$734>=DATE(2024,1,1))*('Daily Data'!$A$4:$A$734<DATE(2024,4,1))*'Daily Data'!$P$4:$P$734) -> 226121 | F4: =E4/D4 -> 0.655541 | G4: n/a | H4: —
A5: Q2 | B5: 2024 | C5: =SUMPRODUCT(('Daily Data'!$A$4:$A$734>=DATE(2024,4,1))*('Daily Data'!$A$4:$A$734<DATE(2024,7,1))*'Daily Data'!$D$4:$D$734) -> 715 | D5: =SUMPRODUCT(('Daily Data'!$A$4:$A$734>=DATE(2024,4,1))*('Daily Data'!$A$4:$A$734<DATE(2024,7,1))*'Daily Data'!$G$4:$G$734) -> 379403 | E5: =SUMPRODUCT(('Daily Data'!$A$4:$A$734>=DATE(2024,4,1))*('Daily Data'!$A$4:$A$734<DATE(2024,7,1))*'Daily Data'!$P$4:$P$734) -> 258079 | F5: =E5/D5 -> 0.68022393 | G5: =IF(D4=0,0,(D5-D4)/D4) -> 0.099916507 | H5: =IF(D5>=D4,"▲ Increase","▼ Decrease") -> ▲ Increase
A6: Q3 | B6: 2024 | C6: =SUMPRODUCT(('Daily Data'!$A$4:$A$734>=DATE(2024,7,1))*('Daily Data'!$A$4:$A$734<DATE(2024,10,1))*'Daily Data'!$D$4:$D$734) -> 564 | D6: =SUMPRODUCT(('Daily Data'!$A$4:$A$734>=DATE(2024,7,1))*('Daily Data'!$A$4:$A$734<DATE(2024,10,1))*'Daily Data'!$G$4:$G$734) -> 300787 | E6: =SUMPRODUCT(('Daily Data'!$A$4:$A$734>=DATE(2024,7,1))*('Daily Data'!$A$4:$A$734<DATE(2024,10,1))*'Daily Data'!$P$4:$P$734) -> 184017 | F6: =E6/D6 -> 0.61178508 | G6: =IF(D5=0,0,(D6-D5)/D5) -> -0.20720975 | H6: =IF(D6>=D5,"▲ Increase","▼ Decrease") -> ▼ Decrease
A7: Q4 | B7: 2024 | C7: =SUMPRODUCT(('Daily Data'!$A$4:$A$734>=DATE(2024,10,1))*('Daily Data'!$A$4:$A$734<DATE(2025,1,1))*'Daily Data'!$D$4:$D$734) -> 964 | D7: =SUMPRODUCT(('Daily Data'!$A$4:$A$734>=DATE(2024,10,1))*('Daily Data'!$A$4:$A$734<DATE(2025,1,1))*'Daily Data'!$G$4:$G$734) -> 514062 | E7: =SUMPRODUCT(('Daily Data'!$A$4:$A$734>=DATE(2024,10,1))*('Daily Data'!$A$4:$A$734<DATE(2025,1,1))*'Daily Data'!$P$4:$P$734) -> 386655 | F7: =E7/D7 -> 0.75215635 | G7: =IF(D6=0,0,(D7-D6)/D6) -> 0.70905657 | H7: =IF(D7>=D6,"▲ Increase","▼ Decrease") -> ▲ Increase
A8: Q1 | B8: 2025 | C8: =SUMPRODUCT(('Daily Data'!$A$4:$A$734>=DATE(2025,1,1))*('Daily Data'!$A$4:$A$734<DATE(2025,4,1))*'Daily Data'!$D$4:$D$734) -> 636 | D8: =SUMPRODUCT(('Daily Data'!$A$4:$A$734>=DATE(2025,1,1))*('Daily Data'!$A$4:$A$734<DATE(2025,4,1))*'Daily Data'!$G$4:$G$734) -> 337060 | E8: =SUMPRODUCT(('Daily Data'!$A$4:$A$734>=DATE(2025,1,1))*('Daily Data'!$A$4:$A$734<DATE(2025,4,1))*'Daily Data'!$P$4:$P$734) -> 218476 | F8: =E8/D8 -> 0.64818133 | G8: =IF(D7=0,0,(D8-D7)/D7) -> -0.34432033 | H8: =IF(D8>=D7,"▲ Increase","▼ Decrease") -> ▼ Decrease
A9: Q2 | B9: 2025 | C9: =SUMPRODUCT(('Daily Data'!$A$4:$A$734>=DATE(2025,4,1))*('Daily Data'!$A$4:$A$734<DATE(2025,7,1))*'Daily Data'!$D$4:$D$734) -> 645 | D9: =SUMPRODUCT(('Daily Data'!$A$4:$A$734>=DATE(2025,4,1))*('Daily Data'!$A$4:$A$734<DATE(2025,7,1))*'Daily Data'!$G$4:$G$734) -> 340402 | E9: =SUMPRODUCT(('Daily Data'!$A$4:$A$734>=DATE(2025,4,1))*('Daily Data'!$A$4:$A$734<DATE(2025,7,1))*'Daily Data'!$P$4:$P$734) -> 220498 | F9: =E9/D9 -> 0.64775765 | G9: =IF(D8=0,0,(D9-D8)/D8) -> 0.0099151486 | H9: =IF(D9>=D8,"▲ Increase","▼ Decrease") -> ▲ Increase
A10: Q3 | B10: 2025 | C10: =SUMPRODUCT(('Daily Data'!$A$4:$A$734>=DATE(2025,7,1))*('Daily Data'!$A$4:$A$734<DATE(2025,10,1))*'Daily Data'!$D$4:$D$734) -> 589 | D10: =SUMPRODUCT(('Daily Data'!$A$4:$A$734>=DATE(2025,7,1))*('Daily Data'!$A$4:$A$734<DATE(2025,10,1))*'Daily Data'!$G$4:$G$734) -> 310308 | E10: =SUMPRODUCT(('Daily Data'!$A$4:$A$734>=DATE(2025,7,1))*('Daily Data'!$A$4:$A$734<DATE(2025,10,1))*'Daily Data'!$P$4:$P$734) -> 193107 | F10: =E10/D10 -> 0.62230751 | G10: =IF(D9=0,0,(D10-D9)/D9) -> -0.088407236 | H10: =IF(D10>=D9,"▲ Increase","▼ Decrease") -> ▼ Decrease
A11: Q4 | B11: 2025 | C11: =SUMPRODUCT(('Daily Data'!$A$4:$A$734>=DATE(2025,10,1))*('Daily Data'!$A$4:$A$734<DATE(2026,1,1))*'Daily Data'!$D$4:$D$734) -> 994 | D11: =SUMPRODUCT(('Daily Data'!$A$4:$A$734>=DATE(2025,10,1))*('Daily Data'!$A$4:$A$734<DATE(2026,1,1))*'Daily Data'!$G$4:$G$734) -> 526516 | E11: =SUMPRODUCT(('Daily Data'!$A$4:$A$734>=DATE(2025,10,1))*('Daily Data'!$A$4:$A$734<DATE(2026,1,1))*'Daily Data'!$P$4:$P$734) -> 398591 | F11: =E11/D11 -> 0.75703492 | G11: =IF(D10=0,0,(D11-D10)/D10) -> 0.6967529 | H11: =IF(D11>=D10,"▲ Increase","▼ Decrease") -> ▲ Increase

Sheet Biannual Trends
A1: BIANNUAL (SEMESTER) TRENDS & COMPARISON
A2: H1=Jan-Jun, H2=Jul-Dec. H2 typically includes rainy-season low (Jul-Sep) followed by holiday peak (Dec). Trend vs prior semester.
A3: Semester | B3: Year | C3: Sessions | D3: Revenue (₱) | E3: Net Income (₱) | F3: Net Margin % | G3: Revenue Sem-on-Sem % | H3: Trend
A4: H1 | B4: 2024 | C4: =SUMPRODUCT(('Daily Data'!$A$4:$A$734>=DATE(2024,1,1))*('Daily Data'!$A$4:$A$734<DATE(2024,7,1))*'Daily Data'!$D$4:$D$734) -> 1359 | D4: =SUMPRODUCT(('Daily Data'!$A$4:$A$734>=DATE(2024,1,1))*('Daily Data'!$A$4:$A$734<DATE(2024,7,1))*'Daily Data'!$G$4:$G$734) -> 724341 | E4: =SUMPRODUCT(('Daily Data'!$A$4:$A$734>=DATE(2024,1,1))*('Daily Data'!$A$4:$A$734<DATE(2024,7,1))*'Daily Data'!$P$4:$P$734) -> 484200 | F4: =E4/D4 -> 0.66846968 | G4: n/a | H4: —
A5: H2 | B5: 2024 | C5: =SUMPRODUCT(('Daily Data'!$A$4:$A$734>=DATE(2024,7,1))*('Daily Data'!$A$4:$A$734<DATE(2025,1,1))*'Daily Data'!$D$4:$D$734) -> 1528 | D5: =SUMPRODUCT(('Daily Data'!$A$4:$A$734>=DATE(2024,7,1))*('Daily Data'!$A$4:$A$734<DATE(2025,1,1))*'Daily Data'!$G$4:$G$734) -> 814849 | E5: =SUMPRODUCT(('Daily Data'!$A$4:$A$734>=DATE(2024,7,1))*('Daily Data'!$A$4:$A$734<DATE(2025,1,1))*'Daily Data'!$P$4:$P$734) -> 570672 | F5: =E5/D5 -> 0.7003408 | G5: =IF(D4=0,0,(D5-D4)/D4) -> 0.1249522 | H5: =IF(D5>=D4,"▲ Increase","▼ Decrease") -> ▲ Increase
A6: H1 | B6: 2025 | C6: =SUMPRODUCT(('Daily Data'!$A$4:$A$734>=DATE(2025,1,1))*('Daily Data'!$A$4:$A$734<DATE(2025,7,1))*'Daily Data'!$D$4:$D$734) -> 1281 | D6: =SUMPRODUCT(('Daily Data'!$A$4:$A$734>=DATE(2025,1,1))*('Daily Data'!$A$4:$A$734<DATE(2025,7,1))*'Daily Data'!$G$4:$G$734) -> 677462 | E6: =SUMPRODUCT(('Daily Data'!$A$4:$A$734>=DATE(2025,1,1))*('Daily Data'!$A$4:$A$734<DATE(2025,7,1))*'Daily Data'!$P$4:$P$734) -> 438974 | F6: =E6/D6 -> 0.64796845 | G6: =IF(D5=0,0,(D6-D5)/D5) -> -0.16860424 | H6: =IF(D6>=D5,"▲ Increase","▼ Decrease") -> ▼ Decrease
A7: H2 | B7: 2025 | C7: =SUMPRODUCT(('Daily Data'!$A$4:$A$734>=DATE(2025,7,1))*('Daily Data'!$A$4:$A$734<DATE(2026,1,1))*'Daily Data'!$D$4:$D$734) -> 1583 | D7: =SUMPRODUCT(('Daily Data'!$A$4:$A$734>=DATE(2025,7,1))*('Daily Data'!$A$4:$A$734<DATE(2026,1,1))*'Daily Data'!$G$4:$G$734) -> 836824 | E7: =SUMPRODUCT(('Daily Data'!$A$4:$A$734>=DATE(2025,7,1))*('Daily Data'!$A$4:$A$734<DATE(2026,1,1))*'Daily Data'!$P$4:$P$734) -> 591698 | F7: =E7/D7 -> 0.7070758 | G7: =IF(D6=0,0,(D7-D6)/D6) -> 0.23523386 | H7: =IF(D7>=D6,"▲ Increase","▼ Decrease") -> ▲ Increase

Sheet Annual & YoY
A1: ANNUAL TOTALS & YEAR-ON-YEAR (YoY) COMPARISON
A2: Compares full-year 2025 performance vs. 2024. Green/▲ = growth, Red/▼ = decline.
A3: Year | B3: Sessions | C3: Revenue (₱) | D3: Total Expenses (₱) | E3: Net Income (₱) | F3: Net Margin % | G3: YoY Revenue Growth % | H3: Trend
A4: 2024 | B4: =SUMPRODUCT((YEAR('Daily Data'!$A$4:$A$734)=2024)*'Daily Data'!$D$4:$D$734) -> 2887 | C4: =SUMPRODUCT((YEAR('Daily Data'!$A$4:$A$734)=2024)*'Daily Data'!$G$4:$G$734) -> 1539190 | D4: =SUMPRODUCT((YEAR('Daily Data'!$A$4:$A$734)=2024)*'Daily Data'!$O$4:$O$734) -> 484318 | E4: =C4-D4 -> 1054872 | F4: =E4/C4 -> 0.68534229 | G4: n/a | H4: —
A5: 2025 | B5: =SUMPRODUCT((YEAR('Daily Data'!$A$4:$A$734)=2025)*'Daily Data'!$D$4:$D$734) -> 2864 | C5: =SUMPRODUCT((YEAR('Daily Data'!$A$4:$A$734)=2025)*'Daily Data'!$G$4:$G$734) -> 1514286 | D5: =SUMPRODUCT((YEAR('Daily Data'!$A$4:$A$734)=2025)*'Daily Data'!$O$4:$O$734) -> 483614 | E5: =C5-D5 -> 1030672 | F5: =E5/C5 -> 0.68063232 | G5: =(C5-C4)/C4 -> -0.016179939 | H5: =IF(C5>=C4,"▲ Increase","▼ Decrease") -> ▼ Decrease
A6: 2-YEAR TOTAL | B6: =SUM(B4:B5) -> 5751 | C6: =SUM(C4:C5) -> 3053476 | D6: =SUM(D4:D5) -> 967932 | E6: =SUM(E4:E5) -> 2085544 | F6: =E6/C6 -> 0.68300651

Sheet AM-PM Demand
A1: AM vs. PM DEMAND COMPARISON & FORECAST
A2: AM = morning sessions (8am-12nn), PM = afternoon/evening (12nn-6pm). Long-duration chemical services (rebond, Brazilian collagen, protein, keratin, hair color) skew toward AM because clients plan ahead for multi-hour appointments. Short services (haircut, manicure, pedicure, eyebrow, foot spa) and weekend walk-ins skew toward PM. Forecast columns project the next period using the trailing 4-week average AM/PM share.
A3: Month | B3: Year | C3: AM Sessions | D3: PM Sessions | E3: AM Revenue (₱) | F3: PM Revenue (₱) | G3: AM Share % | H3: PM Share % | I3: Trend (vs prior month)
A4: Jan | B4: 2024 | C4: =SUMPRODUCT(('Daily Data'!$A$4:$A$734>=DATE(2024,1,1))*('Daily Data'!$A$4:$A$734<DATE(2024,2,1))*'Daily Data'!$E$4:$E$734) -> 50 | D4: =SUMPRODUCT(('Daily Data'!$A$4:$A$734>=DATE(2024,1,1))*('Daily Data'!$A$4:$A$734<DATE(2024,2,1))*'Daily Data'!$F$4:$F$734) -> 129 | E4: =SUMPRODUCT(('Daily Data'!$A$4:$A$734>=DATE(2024,1,1))*('Daily Data'!$A$4:$A$734<DATE(2024,2,1))*'Daily Data'!$H$4:$H$734) -> 67416 | F4: =SUMPRODUCT(('Daily Data'!$A$4:$A$734>=DATE(2024,1,1))*('Daily Data'!$A$4:$A$734<DATE(2024,2,1))*'Daily Data'!$I$4:$I$734) -> 28911 | G4: =E4/(E4+F4) -> 0.69986608 | H4: =F4/(E4+F4) -> 0.30013392 | I4: n/a
A5: Feb | B5: 2024 | C5: =SUMPRODUCT(('Daily Data'!$A$4:$A$734>=DATE(2024,2,1))*('Daily Data'!$A$4:$A$734<DATE(2024,3,1))*'Daily Data'!$E$4:$E$734) -> 76 | D5: =SUMPRODUCT(('Daily Data'!$A$4:$A$734>=DATE(2024,2,1))*('Daily Data'!$A$4:$A$734<DATE(2024,3,1))*'Daily Data'!$F$4:$F$734) -> 142 | E5: =SUMPRODUCT(('Daily Data'!$A$4:$A$734>=DATE(2024,2,1))*('Daily Data'!$A$4:$A$734<DATE(2024,3,1))*'Daily Data'!$H$4:$H$734) -> 84450 | F5: =SUMPRODUCT(('Daily Data'!$A$4:$A$734>=DATE(2024,2,1))*('Daily Data'!$A$4:$A$734<DATE(2024,3,1))*'Daily Data'!$I$4:$I$734) -> 31624 | G5: =E5/(E5+F5) -> 0.72755311 | H5: =F5/(E5+F5) -> 0.27244689 | I5: =IF((E5+F5)>=(E4+F4),"▲ Increase","▼ Decrease") -> ▲ Increase
A6: Mar | B6: 2024 | C6: =SUMPRODUCT(('Daily Data'!$A$4:$A$734>=DATE(2024,3,1))*('Daily Data'!$A$4:$A$734<DATE(2024,4,1))*'Daily Data'!$E$4:$E$734) -> 93 | D6: =SUMPRODUCT(('Daily Data'!$A$4:$A$734>=DATE(2024,3,1))*('Daily Data'!$A$4:$A$734<DATE(2024,4,1))*'Daily Data'!$F$4:$F$734) -> 154 | E6: =SUMPRODUCT(('Daily Data'!$A$4:$A$734>=DATE(2024,3,1))*('Daily Data'!$A$4:$A$734<DATE(2024,4,1))*'Daily Data'!$H$4:$H$734) -> 96634 | F6: =SUMPRODUCT(('Daily Data'!$A$4:$A$734>=DATE(2024,3,1))*('Daily Data'!$A$4:$A$734<DATE(2024,4,1))*'Daily Data'!$I$4:$I$734) -> 35903 | G6: =E6/(E6+F6) -> 0.72910961 | H6: =F6/(E6+F6) -> 0.27089039 | I6: =IF((E6+F6)>=(E5+F5),"▲ Increase","▼ Decrease") -> ▲ Increase
A7: Apr | B7: 2024 | C7: =SUMPRODUCT(('Daily Data'!$A$4:$A$734>=DATE(2024,4,1))*('Daily Data'!$A$4:$A$734<DATE(2024,5,1))*'Daily Data'!$E$4:$E$734) -> 89 | D7: =SUMPRODUCT(('Daily Data'!$A$4:$A$734>=DATE(2024,4,1))*('Daily Data'!$A$4:$A$734<DATE(2024,5,1))*'Daily Data'!$F$4:$F$734) -> 151 | E7: =SUMPRODUCT(('Daily Data'!$A$4:$A$734>=DATE(2024,4,1))*('Daily Data'!$A$4:$A$734<DATE(2024,5,1))*'Daily Data'!$H$4:$H$734) -> 90539 | F7: =SUMPRODUCT(('Daily Data'!$A$4:$A$734>=DATE(2024,4,1))*('Daily Data'!$A$4:$A$734<DATE(2024,5,1))*'Daily Data'!$I$4:$I$734) -> 36970 | G7: =E7/(E7+F7) -> 0.71005968 | H7: =F7/(E7+F7) -> 0.28994032 | I7: =IF((E7+F7)>=(E6+F6),"▲ Increase","▼ Decrease") -> ▼ Decrease
A8: May | B8: 2024 | C8: =SUMPRODUCT(('Daily Data'!$A$4:$A$734>=DATE(2024,5,1))*('Daily Data'!$A$4:$A$734<DATE(2024,6,1))*'Daily Data'!$E$4:$E$734) -> 110 | D8: =SUMPRODUCT(('Daily Data'!$A$4:$A$734>=DATE(2024,5,1))*('Daily Data'!$A$4:$A$734<DATE(2024,6,1))*'Daily Data'!$F$4:$F$734) -> 164 | E8: =SUMPRODUCT(('Daily Data'!$A$4:$A$734>=DATE(2024,5,1))*('Daily Data'!$A$4:$A$734<DATE(2024,6,1))*'Daily Data'!$H$4:$H$734) -> 104012 | F8: =SUMPRODUCT(('Daily Data'!$A$4:$A$734>=DATE(2024,5,1))*('Daily Data'!$A$4:$A$734<DATE(2024,6,1))*'Daily Data'!$I$4:$I$734) -> 41604 | G8: =E8/(E8+F8) -> 0.71428964 | H8: =F8/(E8+F8) -> 0.28571036 | I8: =IF((E8+F8)>=(E7+F7),"▲ Increase","▼ Decrease") -> ▲ Increase
A9: Jun | B9: 2024 | C9: =SUMPRODUCT(('Daily Data'!$A$4:$A$734>=DATE(2024,6,1))*('Daily Data'!$A$4:$A$734<DATE(2024,7,1))*'Daily Data'!$E$4:$E$734) -> 64 | D9: =SUMPRODUCT(('Daily Data'!$A$4:$A$734>=DATE(2024,6,1))*('Daily Data'!$A$4:$A$734<DATE(2024,7,1))*'Daily Data'!$F$4:$F$734) -> 137 | E9: =SUMPRODUCT(('Daily Data'!$A$4:$A$734>=DATE(2024,6,1))*('Daily Data'!$A$4:$A$734<DATE(2024,7,1))*'Daily Data'!$H$4:$H$734) -> 76177 | F9: =SUMPRODUCT(('Daily Data'!$A$4:$A$734>=DATE(2024,6,1))*('Daily Data'!$A$4:$A$734<DATE(2024,7,1))*'Daily Data'!$I$4:$I$734) -> 30102 | G9: =E9/(E9+F9) -> 0.71676437 | H9: =F9/(E9+F9) -> 0.28323563 | I9: =IF((E9+F9)>=(E8+F8),"▲ Increase","▼ Decrease") -> ▼ Decrease
A10: Jul | B10: 2024 | C10: =SUMPRODUCT(('Daily Data'!$A$4:$A$734>=DATE(2024,7,1))*('Daily Data'!$A$4:$A$734<DATE(2024,8,1))*'Daily Data'!$E$4:$E$734) -> 44 | D10: =SUMPRODUCT(('Daily Data'!$A$4:$A$734>=DATE(2024,7,1))*('Daily Data'!$A$4:$A$734<DATE(2024,8,1))*'Daily Data'!$F$4:$F$734) -> 137 | E10: =SUMPRODUCT(('Daily Data'!$A$4:$A$734>=DATE(2024,7,1))*('Daily Data'!$A$4:$A$734<DATE(2024,8,1))*'Daily Data'!$H$4:$H$734) -> 60477 | F10: =SUMPRODUCT(('Daily Data'!$A$4:$A$734>=DATE(2024,7,1))*('Daily Data'!$A$4:$A$734<DATE(2024,8,1))*'Daily Data'!$I$4:$I$734) -> 36084 | G10: =E10/(E10+F10) -> 0.62630876 | H10: =F10/(E10+F10) -> 0.37369124 | I10: =IF((E10+F10)>=(E9+F9),"▲ Increase","▼ Decrease") -> ▼ Decrease
A11: Aug | B11: 2024 | C11: =SUMPRODUCT(('Daily Data'!$A$4:$A$734>=DATE(2024,8,1))*('Daily Data'!$A$4:$A$734<DATE(2024,9,1))*'Daily Data'!$E$4:$E$734) -> 54 | D11: =SUMPRODUCT(('Daily Data'!$A$4:$A$734>=DATE(2024,8,1))*('Daily Data'!$A$4:$A$734<DATE(2024,9,1))*'Daily Data'!$F$4:$F$734) -> 138 | E11: =SUMPRODUCT(('Daily Data'!$A$4:$A$734>=DATE(2024,8,1))*('Daily Data'!$A$4:$A$734<DATE(2024,9,1))*'Daily Data'!$H$4:$H$734) -> 68978 | F11: =SUMPRODUCT(('Daily Data'!$A$4:$A$734>=DATE(2024,8,1))*('Daily Data'!$A$4:$A$734<DATE(2024,9,1))*'Daily Data'!$I$4:$I$734) -> 32957 | G11: =E11/(E11+F11) -> 0.67668612 | H11: =F11/(E11+F11) -> 0.32331388 | I11: =IF((E11+F11)>=(E10+F10),"▲ Increase","▼ Decrease") -> ▲ Increase
A12: Sep | B12: 2024 | C12: =SUMPRODUCT(('Daily Data'!$A$4:$A$734>=DATE(2024,9,1))*('Daily Data'!$A$4:$A$734<DATE(2024,10,1))*'Daily Data'!$E$4:$E$734) -> 58 | D12: =SUMPRODUCT(('Daily Data'!$A$4:$A$734>=DATE(2024,9,1))*('Daily Data'!$A$4:$A$734<DATE(2024,10,1))*'Daily Data'!$F$4:$F$734) -> 133 | E12: =SUMPRODUCT(('Daily Data'!$A$4:$A$734>=DATE(2024,9,1))*('Daily Data'!$A$4:$A$734<DATE(2024,10,1))*'Daily Data'!$H$4:$H$734) -> 71908 | F12: =SUMPRODUCT(('Daily Data'!$A$4:$A$734>=DATE(2024,9,1))*('Daily Data'!$A$4:$A$734<DATE(2024,10,1))*'Daily Data'!$I$4:$I$734) -> 30384 | G12: =E12/(E12+F12) -> 0.70296797 | H12: =F12/(E12+F12) -> 0.29703203 | I12: =IF((E12+F12)>=(E11+F11),"▲ Increase","▼ Decrease") -> ▲ Increase
A13: Oct | B13: 2024 | C13: =SUMPRODUCT(('Daily Data'!$A$4:$A$734>=DATE(2024,10,1))*('Daily Data'!$A$4:$A$734<DATE(2024,11,1))*'Daily Data'!$E$4:$E$734) -> 77 | D13: =SUMPRODUCT(('Daily Data'!$A$4:$A$734>=DATE(2024,10,1))*('Daily Data'!$A$4:$A$734<DATE(2024,11,1))*'Daily Data'!$F$4:$F$734) -> 145 | E13: =SUMPRODUCT(('Daily Data'!$A$4:$A$734>=DATE(2024,10,1))*('Daily Data'!$A$4:$A$734<DATE(2024,11,1))*'Daily Data'!$H$4:$H$734) -> 87702 | F13: =SUMPRODUCT(('Daily Data'!$A$4:$A$734>=DATE(2024,10,1))*('Daily Data'!$A$4:$A$734<DATE(2024,11,1))*'Daily Data'!$I$4:$I$734) -> 32051 | G13: =E13/(E13+F13) -> 0.73235744 | H13: =F13/(E13+F13) -> 0.26764256 | I13: =IF((E13+F13)>=(E12+F12),"▲ Increase","▼ Decrease") -> ▲ Increase
A14: Nov | B14: 2024 | C14: =SUMPRODUCT(('Daily Data'!$A$4:$A$734>=DATE(2024,11,1))*('Daily Data'!$A$4:$A$734<DATE(2024,12,1))*'Daily Data'!$E$4:$E$734) -> 79 | D14: =SUMPRODUCT(('Daily Data'!$A$4:$A$734>=DATE(2024,11,1))*('Daily Data'!$A$4:$A$734<DATE(2024,12,1))*'Daily Data'!$F$4:$F$734) -> 151 | E14: =SUMPRODUCT(('Daily Data'!$A$4:$A$734>=DATE(2024,11,1))*('Daily Data'!$A$4:$A$734<DATE(2024,12,1))*'Daily Data'!$H$4:$H$734) -> 86737 | F14: =SUMPRODUCT(('Daily Data'!$A$4:$A$734>=DATE(2024,11,1))*('Daily Data'!$A$4:$A$734<DATE(2024,12,1))*'Daily Data'!$I$4:$I$734) -> 35691 | G14: =E14/(E14+F14) -> 0.70847355 | H14: =F14/(E14+F14) -> 0.29152645 | I14: =IF((E14+F14)>=(E13+F13),"▲ Increase","▼ Decrease") -> ▲ Increase
A15: Dec | B15: 2024 | C15: =SUMPRODUCT(('Daily Data'!$A$4:$A$734>=DATE(2024,12,1))*('Daily Data'!$A$4:$A$734<DATE(2025,1,1))*'Daily Data'!$E$4:$E$734) -> 247 | D15: =SUMPRODUCT(('Daily Data'!$A$4:$A$734>=DATE(2024,12,1))*('Daily Data'!$A$4:$A$734<DATE(2025,1,1))*'Daily Data'!$F$4:$F$734) -> 265 | E15: =SUMPRODUCT(('Daily Data'!$A$4:$A$734>=DATE(2024,12,1))*('Daily Data'!$A$4:$A$734<DATE(2025,1,1))*'Daily Data'!$H$4:$H$734) -> 187237 | F15: =SUMPRODUCT(('Daily Data'!$A$4:$A$734>=DATE(2024,12,1))*('Daily Data'!$A$4:$A$734<DATE(2025,1,1))*'Daily Data'!$I$4:$I$734) -> 84645 | G15: =E15/(E15+F15) -> 0.68867008 | H15: =F15/(E15+F15) -> 0.31132992 | I15: =IF((E15+F15)>=(E14+F14),"▲ Increase","▼ Decrease") -> ▲ Increase
A16: Jan | B16: 2025 | C16: =SUMPRODUCT(('Daily Data'!$A$4:$A$734>=DATE(2025,1,1))*('Daily Data'!$A$4:$A$734<DATE(2025,2,1))*'Daily Data'!$E$4:$E$734) -> 43 | D16: =SUMPRODUCT(('Daily Data'!$A$4:$A$734>=DATE(2025,1,1))*('Daily Data'!$A$4:$A$734<DATE(2025,2,1))*'Daily Data'!$F$4:$F$734) -> 138 | E16: =SUMPRODUCT(('Daily Data'!$A$4:$A$734>=DATE(2025,1,1))*('Daily Data'!$A$4:$A$734<DATE(2025,2,1))*'Daily Data'!$H$4:$H$734) -> 59797 | F16: =SUMPRODUCT(('Daily Data'!$A$4:$A$734>=DATE(2025,1,1))*('Daily Data'!$A$4:$A$734<DATE(2025,2,1))*'Daily Data'!$I$4:$I$734) -> 36693 | G16: =E16/(E16+F16) -> 0.61972225 | H16: =F16/(E16+F16) -> 0.38027775 | I16: =IF((E16+F16)>=(E15+F15),"▲ Increase","▼ Decrease") -> ▼ Decrease
A17: Feb | B17: 2025 | C17: =SUMPRODUCT(('Daily Data'!$A$4:$A$734>=DATE(2025,2,1))*('Daily Data'!$A$4:$A$734<DATE(2025,3,1))*'Daily Data'!$E$4:$E$734) -> 81 | D17: =SUMPRODUCT(('Daily Data'!$A$4:$A$734>=DATE(2025,2,1))*('Daily Data'!$A$4:$A$734<DATE(2025,3,1))*'Daily Data'!$F$4:$F$734) -> 136 | E17: =SUMPRODUCT(('Daily Data'!$A$4:$A$734>=DATE(2025,2,1))*('Daily Data'!$A$4:$A$734<DATE(2025,3,1))*'Daily Data'!$H$4:$H$734) -> 85699 | F17: =SUMPRODUCT(('Daily Data'!$A$4:$A$734>=DATE(2025,2,1))*('Daily Data'!$A$4:$A$734<DATE(2025,3,1))*'Daily Data'!$I$4:$I$734) -> 30031 | G17: =E17/(E17+F17) -> 0.74050808 | H17: =F17/(E17+F17) -> 0.25949192 | I17: =IF((E17+F17)>=(E16+F16),"▲ Increase","▼ Decrease") -> ▲ Increase
A18: Mar | B18: 2025 | C18: =SUMPRODUCT(('Daily Data'!$A$4:$A$734>=DATE(2025,3,1))*('Daily Data'!$A$4:$A$734<DATE(2025,4,1))*'Daily Data'!$E$4:$E$734) -> 87 | D18: =SUMPRODUCT(('Daily Data'!$A$4:$A$734>=DATE(2025,3,1))*('Daily Data'!$A$4:$A$734<DATE(2025,4,1))*'Daily Data'!$F$4:$F$734) -> 151 | E18: =SUMPRODUCT(('Daily Data'!$A$4:$A$734>=DATE(2025,3,1))*('Daily Data'!$A$4:$A$734<DATE(2025,4,1))*'Daily Data'!$H$4:$H$734) -> 87839 | F18: =SUMPRODUCT(('Daily Data'!$A$4:$A$734>=DATE(2025,3,1))*('Daily Data'!$A$4:$A$734<DATE(2025,4,1))*'Daily Data'!$I$4:$I$734) -> 37003 | G18: =E18/(E18+F18) -> 0.70360135 | H18: =F18/(E18+F18) -> 0.29639865 | I18: =IF((E18+F18)>=(E17+F17),"▲ Increase","▼ Decrease") -> ▲ Increase
A19: Apr | B19: 2025 | C19: =SUMPRODUCT(('Daily Data'!$A$4:$A$734>=DATE(2025,4,1))*('Daily Data'!$A$4:$A$734<DATE(2025,5,1))*'Daily Data'!$E$4:$E$734) -> 67 | D19: =SUMPRODUCT(('Daily Data'!$A$4:$A$734>=DATE(2025,4,1))*('Daily Data'!$A$4:$A$734<DATE(2025,5,1))*'Daily Data'!$F$4:$F$734) -> 141 | E19: =SUMPRODUCT(('Daily Data'!$A$4:$A$734>=DATE(2025,4,1))*('Daily Data'!$A$4:$A$734<DATE(2025,5,1))*'Daily Data'!$H$4:$H$734) -> 77669 | F19: =SUMPRODUCT(('Daily Data'!$A$4:$A$734>=DATE(2025,4,1))*('Daily Data'!$A$4:$A$734<DATE(2025,5,1))*'Daily Data'!$I$4:$I$734) -> 31811 | G19: =E19/(E19+F19) -> 0.70943551 | H19: =F19/(E19+F19) -> 0.29056449 | I19: =IF((E19+F19)>=(E18+F18),"▲ Increase","▼ Decrease") -> ▼ Decrease
A20: May | B20: 2025 | C20: =SUMPRODUCT(('Daily Data'!$A$4:$A$734>=DATE(2025,5,1))*('Daily Data'!$A$4:$A$734<DATE(2025,6,1))*'Daily Data'!$E$4:$E$734) -> 88 | D20: =SUMPRODUCT(('Daily Data'!$A$4:$A$734>=DATE(2025,5,1))*('Daily Data'!$A$4:$A$734<DATE(2025,6,1))*'Daily Data'!$F$4:$F$734) -> 150 | E20: =SUMPRODUCT(('Daily Data'!$A$4:$A$734>=DATE(2025,5,1))*('Daily Data'!$A$4:$A$734<DATE(2025,6,1))*'Daily Data'!$H$4:$H$734) -> 88673 | F20: =SUMPRODUCT(('Daily Data'!$A$4:$A$734>=DATE(2025,5,1))*('Daily Data'!$A$4:$A$734<DATE(2025,6,1))*'Daily Data'!$I$4:$I$734) -> 35928 | G20: =E20/(E20+F20) -> 0.7116556 | H20: =F20/(E20+F20) -> 0.2883444 | I20: =IF((E20+F20)>=(E19+F19),"▲ Increase","▼ Decrease") -> ▲ Increase
A21: Jun | B21: 2025 | C21: =SUMPRODUCT(('Daily Data'!$A$4:$A$734>=DATE(2025,6,1))*('Daily Data'!$A$4:$A$734<DATE(2025,7,1))*'Daily Data'!$E$4:$E$734) -> 62 | D21: =SUMPRODUCT(('Daily Data'!$A$4:$A$734>=DATE(2025,6,1))*('Daily Data'!$A$4:$A$734<DATE(2025,7,1))*'Daily Data'!$F$4:$F$734) -> 137 | E21: =SUMPRODUCT(('Daily Data'!$A$4:$A$734>=DATE(2025,6,1))*('Daily Data'!$A$4:$A$734<DATE(2025,7,1))*'Daily Data'!$H$4:$H$734) -> 73984 | F21: =SUMPRODUCT(('Daily Data'!$A$4:$A$734>=DATE(2025,6,1))*('Daily Data'!$A$4:$A$734<DATE(2025,7,1))*'Daily Data'!$I$4:$I$734) -> 32337 | G21: =E21/(E21+F21) -> 0.69585501 | H21: =F21/(E21+F21) -> 0.30414499 | I21: =IF((E21+F21)>=(E20+F20),"▲ Increase","▼ Decrease") -> ▼ Decrease
A22: Jul | B22: 2025 | C22: =SUMPRODUCT(('Daily Data'!$A$4:$A$734>=DATE(2025,7,1))*('Daily Data'!$A$4:$A$734<DATE(2025,8,1))*'Daily Data'!$E$4:$E$734) -> 55 | D22: =SUMPRODUCT(('Daily Data'!$A$4:$A$734>=DATE(2025,7,1))*('Daily Data'!$A$4:$A$734<DATE(2025,8,1))*'Daily Data'!$F$4:$F$734) -> 137 | E22: =SUMPRODUCT(('Daily Data'!$A$4:$A$734>=DATE(2025,7,1))*('Daily Data'!$A$4:$A$734<DATE(2025,8,1))*'Daily Data'!$H$4:$H$734) -> 70105 | F22: =SUMPRODUCT(('Daily Data'!$A$4:$A$734>=DATE(2025,7,1))*('Daily Data'!$A$4:$A$734<DATE(2025,8,1))*'Daily Data'!$I$4:$I$734) -> 30898 | G22: =E22/(E22+F22) -> 0.69408829 | H22: =F22/(E22+F22) -> 0.30591171 | I22: =IF((E22+F22)>=(E21+F21),"▲ Increase","▼ Decrease") -> ▼ Decrease
A23: Aug | B23: 2025 | C23: =SUMPRODUCT(('Daily Data'!$A$4:$A$734>=DATE(2025,8,1))*('Daily Data'!$A$4:$A$734<DATE(2025,9,1))*'Daily Data'!$E$4:$E$734) -> 61 | D23: =SUMPRODUCT(('Daily Data'!$A$4:$A$734>=DATE(2025,8,1))*('Daily Data'!$A$4:$A$734<DATE(2025,9,1))*'Daily Data'!$F$4:$F$734) -> 138 | E23: =SUMPRODUCT(('Daily Data'!$A$4:$A$734>=DATE(2025,8,1))*('Daily Data'!$A$4:$A$734<DATE(2025,9,1))*'Daily Data'!$H$4:$H$734) -> 74146 | F23: =SUMPRODUCT(('Daily Data'!$A$4:$A$734>=DATE(2025,8,1))*('Daily Data'!$A$4:$A$734<DATE(2025,9,1))*'Daily Data'!$I$4:$I$734) -> 29800 | G23: =E23/(E23+F23) -> 0.71331268 | H23: =F23/(E23+F23) -> 0.28668732 | I23: =IF((E23+F23)>=(E22+F22),"▲ Increase","▼ Decrease") -> ▲ Increase
A24: Sep | B24: 2025 | C24: =SUMPRODUCT(('Daily Data'!$A$4:$A$734>=DATE(2025,9,1))*('Daily Data'!$A$4:$A$734<DATE(2025,10,1))*'Daily Data'!$E$4:$E$734) -> 60 | D24: =SUMPRODUCT(('Daily Data'!$A$4:$A$734>=DATE(2025,9,1))*('Daily Data'!$A$4:$A$734<DATE(2025,10,1))*'Daily Data'!$F$4:$F$734) -> 138 | E24: =SUMPRODUCT(('Daily Data'!$A$4:$A$734>=DATE(2025,9,1))*('Daily Data'!$A$4:$A$734<DATE(2025,10,1))*'Daily Data'!$H$4:$H$734) -> 71536 | F24: =SUMPRODUCT(('Daily Data'!$A$4:$A$734>=DATE(2025,9,1))*('Daily Data'!$A$4:$A$734<DATE(2025,10,1))*'Daily Data'!$I$4:$I$734) -> 33824 | G24: =E24/(E24+F24) -> 0.67896735 | H24: =F24/(E24+F24) -> 0.32103265 | I24: =IF((E24+F24)>=(E23+F23),"▲ Increase","▼ Decrease") -> ▲ Increase
A25: Oct | B25: 2025 | C25: =SUMPRODUCT(('Daily Data'!$A$4:$A$734>=DATE(2025,10,1))*('Daily Data'!$A$4:$A$734<DATE(2025,11,1))*'Daily Data'!$E$4:$E$734) -> 84 | D25: =SUMPRODUCT(('Daily Data'!$A$4:$A$734>=DATE(2025,10,1))*('Daily Data'!$A$4:$A$734<DATE(2025,11,1))*'Daily Data'!$F$4:$F$734) -> 150 | E25: =SUMPRODUCT(('Daily Data'!$A$4:$A$734>=DATE(2025,10,1))*('Daily Data'!$A$4:$A$734<DATE(2025,11,1))*'Daily Data'!$H$4:$H$734) -> 89537 | F25: =SUMPRODUCT(('Daily Data'!$A$4:$A$734>=DATE(2025,10,1))*('Daily Data'!$A$4:$A$734<DATE(2025,11,1))*'Daily Data'!$I$4:$I$734) -> 33524 | G25: =E25/(E25+F25) -> 0.72758226 | H25: =F25/(E25+F25) -> 0.27241774 | I25: =IF((E25+F25)>=(E24+F24),"▲ Increase","▼ Decrease") -> ▲ Increase
A26: Nov | B26: 2025 | C26: =SUMPRODUCT(('Daily Data'!$A$4:$A$734>=DATE(2025,11,1))*('Daily Data'!$A$4:$A$734<DATE(2025,12,1))*'Daily Data'!$E$4:$E$734) -> 92 | D26: =SUMPRODUCT(('Daily Data'!$A$4:$A$734>=DATE(2025,11,1))*('Daily Data'!$A$4:$A$734<DATE(2025,12,1))*'Daily Data'!$F$4:$F$734) -> 150 | E26: =SUMPRODUCT(('Daily Data'!$A$4:$A$734>=DATE(2025,11,1))*('Daily Data'!$A$4:$A$734<DATE(2025,12,1))*'Daily Data'!$H$4:$H$734) -> 92496 | F26: =SUMPRODUCT(('Daily Data'!$A$4:$A$734>=DATE(2025,11,1))*('Daily Data'!$A$4:$A$734<DATE(2025,12,1))*'Daily Data'!$I$4:$I$734) -> 35336 | G26: =E26/(E26+F26) -> 0.72357469 | H26: =F26/(E26+F26) -> 0.27642531 | I26: =IF((E26+F26)>=(E25+F25),"▲ Increase","▼ Decrease") -> ▲ Increase
A27: Dec | B27: 2025 | C27: =SUMPRODUCT(('Daily Data'!$A$4:$A$734>=DATE(2025,12,1))*('Daily Data'!$A$4:$A$734<DATE(2026,1,1))*'Daily Data'!$E$4:$E$734) -> 260 | D27: =SUMPRODUCT(('Daily Data'!$A$4:$A$734>=DATE(2025,12,1))*('Daily Data'!$A$4:$A$734<DATE(2026,1,1))*'Daily Data'!$F$4:$F$734) -> 258 | E27: =SUMPRODUCT(('Daily Data'!$A$4:$A$734>=DATE(2025,12,1))*('Daily Data'!$A$4:$A$734<DATE(2026,1,1))*'Daily Data'!$H$4:$H$734) -> 193239 | F27: =SUMPRODUCT(('Daily Data'!$A$4:$A$734>=DATE(2025,12,1))*('Daily Data'!$A$4:$A$734<DATE(2026,1,1))*'Daily Data'!$I$4:$I$734) -> 82384 | G27: =E27/(E27+F27) -> 0.70109896 | H27: =F27/(E27+F27) -> 0.29890104 | I27: =IF((E27+F27)>=(E26+F26),"▲ Increase","▼ Decrease") -> ▲ Increase
A28: 2-YR AVERAGE | C28: =AVERAGE(C4:C27) -> 86.708333 | D28: =AVERAGE(D4:D27) -> 152.91667 | E28: =AVERAGE(E4:E27) -> 89457.792 | F28: =AVERAGE(F4:F27) -> 37770.625 | G28: =E28/(E28+F28) -> 0.70312745 | H28: =F28/(E28+F28) -> 0.29687255
A30: FORECAST: JAN 2026 | C30: =C27*(0.8/1.55) -> 134.19355 | D30: =D27*(0.8/1.55) -> 133.16129 | E30: =E27*(0.8/1.55) -> 99736.258 | F30: =F27*(0.8/1.55) -> 42520.774 | G30: =E30/(E30+F30) -> 0.70109896 | H30: =F30/(E30+F30) -> 0.29890104 | I30: Projected (Jan = post-holiday dip, seasonal index 0.80 vs Dec 1.55)

Sheet Inventory Tracker
A1: CHEMICAL INVENTORY TRACKER — JAN 2024 to DEC 2025 (24 MONTHS)
A2: 🔴 STOCKOUT = negative closing stock | 🟠 CRITICAL = zero stock | 🟡 LOW = below 40% of buffer | ✅ OK = within buffer | 🔵 OVERSTOCK = up to 2.5x buffer | 🟣 EXCESS = beyond 2.5x buffer, risk of expiry
A3: CHEMICAL / PRODUCT | B3: UNIT | C3: MONTH | D3: OPENING STOCK | E3: PURCHASED | F3: USED | G3: CLOSING STOCK | H3: STATUS | I3: NOTES / ACTION
A4: Hair Color (Mixed Shades) | B4: tubes | C4: JAN '24 | D4: 289 | E4: 85 | F4: 109 | G4: 265 | H4: OVERSTOCK | I4: 🔵 Sobra ang stock. Bawasan ang order.
C5: FEB '24 | D5: 265 | E5: 115 | F5: 138 | G5: 242 | H5: OK | I5: ✅ Stock level okay.
C6: MAR '24 | D6: 242 | E6: 129 | F6: 147 | G6: 224 | H6: OK | I6: ✅ Stock level okay.
C7: APR '24 | D7: 224 | E7: 112 | F7: 131 | G7: 205 | H7: OK | I7: ✅ Stock level okay.
C8: MAY '24 | D8: 205 | E8: 121 | F8: 143 | G8: 183 | H8: OK | I8: ✅ Stock level okay.
C9: JUN '24 | D9: 183 | E9: 88 | F9: 111 | G9: 160 | H9: OK | I9: ✅ Stock level okay.
C10: JUL '24 | D10: 160 | E10: 94 | F10: 108 | G10: 146 | H10: OK | I10: ✅ Stock level okay.
C11: AUG '24 | D11: 146 | E11: 80 | F11: 106 | G11: 120 | H11: OK | I11: ✅ Stock level okay.
C12: SEP '24 | D12: 120 | E12: 107 | F12: 121 | G12: 106 | H12: OK | I12: ✅ Stock level okay.
C13: OCT '24 | D13: 106 | E13: 107 | F13: 134 | G13: 79 | H13: OK | I13: ✅ Stock level okay.
C14: NOV '24 | D14: 80 | E14: 60 | F14: 135 | G14: 5 | H14: LOW | I14: 🟡 Mababa na ang stock. Mag-reorder soon.
C15: DEC '24 | D15: 5 | E15: 50 | F15: 178 | G15: -123 | H15: STOCKOUT | I15: ⚠ Nagkulang! Hindi naserbisyuhan lahat ng clients.
C16: JAN '25 | D16: 0 | E16: 90 | F16: 109 | G16: -19 | H16: STOCKOUT | I16: ⚠ Nagkulang! Hindi naserbisyuhan lahat ng clients.
... C27: DEC '25 | D27: 229 | E27: 225 | F27: 203 | G27: 251 | H27: OK | I27: ✅ Stock level okay.
A29: Cellophane Treatment | B29: sachets | C29: JAN '24 | D29: 232 | E29: 76 | F29: 94 | G29: 214 | H29: OVERSTOCK | I29: 🔵 Sobra ang stock. Bawasan ang order.
C30: FEB '24 | D30: 214 | E30: 93 | F30: 108 | G30: 199 | H30: OK | I30: ✅ Stock level okay.
C31: MAR '24 | D31: 199 | E31: 98 | F31: 119 | G31: 178 | H31: OK | I31: ✅ Stock level okay.
C32: APR '24 | D32: 178 | E32: 106 | F32: 119 | G32: 165 | H32: OK | I32: ✅ Stock level okay.
C33: MAY '24 | D33: 165 | E33: 103 | F33: 121 | G33: 147 | H33: OK | I33: ✅ Stock level okay.
C34: JUN '24 | D34: 147 | E34: 83 | F34: 98 | G34: 132 | H34: OK | I34: ✅ Stock level okay.
C35: JUL '24 | D35: 132 | E35: 70 | F35: 92 | G35: 110 | H35: OK | I35: ✅ Stock level okay.
C36: AUG '24 | D36: 110 | E36: 79 | F36: 98 | G36: 91 | H36: OK | I36: ✅ Stock level okay.
C37: SEP '24 | D37: 91 | E37: 84 | F37: 96 | G37: 79 | H37: OK | I37: ✅ Stock level okay.
C38: OCT '24 | D38: 79 | E38: 84 | F38: 103 | G38: 60 | H38: OK | I38: ✅ Stock level okay.
C39: NOV '24 | D39: 60 | E39: 40 | F39: 75 | G39: 25 | H39: LOW | I39: 🟡 Mababa na ang stock. Mag-reorder soon.
C40: DEC '24 | D40: 25 | E40: 30 | F40: 155 | G40: -100 | H40: STOCKOUT | I40: ⚠ Nagkulang! Hindi naserbisyuhan lahat ng clients.
C41: JAN '25 | D41: 0 | E41: 80 | F41: 99 | G41: -19 | H41: STOCKOUT | I41: ⚠ Nagkulang! Hindi naserbisyuhan lahat ng clients.
... C52: DEC '25 | D52: 215 | E52: 196 | F52: 166 | G52: 245 | H52: OK | I52: ✅ Stock level okay.
A54: Rebonding Cream | B54: kits | C54: JAN '24 | D54: 63 | E54: 16 | F54: 18 | G54: 61 | H54: EXCESS | I54: 🟣 Malabis na stock! Maaaring mag-expire.
C55: FEB '24 | D55: 61 | E55: 17 | F55: 22 | G55: 56 | H55: OVERSTOCK | I55: 🔵 Sobra ang stock. Bawasan ang order.
C56: MAR '24 | D56: 56 | E56: 19 | F56: 22 | G56: 53 | H56: OVERSTOCK | I56: 🔵 Sobra ang stock. Bawasan ang order.
C57: APR '24 | D57: 53 | E57: 17 | F57: 20 | G57: 50 | H57: OVERSTOCK | I57: 🔵 Sobra ang stock. Bawasan ang order.
C58: MAY '24 | D58: 50 | E58: 18 | F58: 23 | G58: 45 | H58: OK | I58: ✅ Stock level okay.
C59: JUN '24 | D59: 45 | E59: 15 | F59: 17 | G59: 43 | H59: OVERSTOCK | I59: 🔵 Sobra ang stock. Bawasan ang order.
C60: JUL '24 | D60: 43 | E60: 13 | F60: 16 | G60: 40 | H60: OVERSTOCK | I60: 🔵 Sobra ang stock. Bawasan ang order.
C61: AUG '24 | D61: 40 | E61: 15 | F61: 17 | G61: 38 | H61: OVERSTOCK | I61: 🔵 Sobra ang stock. Bawasan ang order.
C62: SEP '24 | D62: 38 | E62: 12 | F62: 17 | G62: 33 | H62: OK | I62: ✅ Stock level okay.
C63: OCT '24 | D63: 33 | E63: 19 | F63: 21 | G63: 31 | H63: OK | I63: ✅ Stock level okay.
C64: NOV '24 | D64: 30 | E64: 80 | F64: 22 | G64: 88 | H64: EXCESS | I64: 🟣 Malabis na stock! Maaaring mag-expire.
C65: DEC '24 | D65: 88 | E65: 60 | F65: 30 | G65: 118 | H65: EXCESS | I65: 🟣 Malabis na stock! Maaaring mag-expire.
C66: JAN '25 | D66: 118 | E66: 20 | F66: 17 | G66: 121 | H66: EXCESS | I66: 🟣 Malabis na stock! Maaaring mag-expire.
... C77: DEC '25 | D77: 127 | E77: 44 | F77: 31 | G77: 140 | H77: EXCESS | I77: 🟣 Malabis na stock! Maaaring mag-expire.
A79: Neutralizer | B79: bottles | C79: JAN '24 | D79: 54 | E79: 12 | F79: 15 | G79: 51 | H79: EXCESS | I79: 🟣 Malabis na stock! Maaaring mag-expire.
C80: FEB '24 | D80: 51 | E80: 17 | F80: 20 | G80: 48 | H80: OVERSTOCK | I80: 🔵 Sobra ang stock. Bawasan ang order.
C81: MAR '24 | D81: 48 | E81: 17 | F81: 20 | G81: 45 | H81: OVERSTOCK | I81: 🔵 Sobra ang stock. Bawasan ang order.
C82: APR '24 | D82: 45 | E82: 16 | F82: 20 | G82: 41 | H82: OK | I82: ✅ Stock level okay.
C83: MAY '24 | D83: 41 | E83: 21 | F83: 22 | G83: 40 | H83: OK | I83: ✅ Stock level okay.
C84: JUN '24 | D84: 40 | E84: 14 | F84: 17 | G84: 37 | H84: OVERSTOCK | I84: 🔵 Sobra ang stock. Bawasan ang order.
C85: JUL '24 | D85: 37 | E85: 12 | F85: 15 | G85: 34 | H85: OVERSTOCK | I85: 🔵 Sobra ang stock. Bawasan ang order.
C86: AUG '24 | D86: 34 | E86: 12 | F86: 15 | G86: 31 | H86: OK | I86: ✅ Stock level okay.
C87: SEP '24 | D87: 31 | E87: 11 | F87: 15 | G87: 27 | H87: OK | I87: ✅ Stock level okay.
C88: OCT '24 | D88: 27 | E88: 14 | F88: 17 | G88: 24 | H88: OK | I88: ✅ Stock level okay.
C89: NOV '24 | D89: 25 | E89: 70 | F89: 20 | G89: 75 | H89: EXCESS | I89: 🟣 Malabis na stock! Maaaring mag-expire.
C90: DEC '24 | D90: 75 | E90: 50 | F90: 28 | G90: 97 | H90: EXCESS | I90: 🟣 Malabis na stock! Maaaring mag-expire.
C91: JAN '25 | D91: 97 | E91: 15 | F91: 14 | G91: 98 | H91: EXCESS | I91: 🟣 Malabis na stock! Maaaring mag-expire.
... C102: DEC '25 | D102: 98 | E102: 45 | F102: 31 | G102: 112 | H102: EXCESS | I102: 🟣 Malabis na stock! Maaaring mag-expire.
A104: Keratin Solution | B104: bottles | C104: JAN '24 | D104: 32 | E104: 6 | F104: 7 | G104: 31 | H104: EXCESS | I104: 🟣 Malabis na stock! Maaaring mag-expire.
C105: FEB '24 | D105: 31 | E105: 7 | F105: 8 | G105: 30 | H105: EXCESS | I105: 🟣 Malabis na stock! Maaaring mag-expire.
C106: MAR '24 | D106: 30 | E106: 7 | F106: 9 | G106: 28 | H106: OVERSTOCK | I106: 🔵 Sobra ang stock. Bawasan ang order.
C107: APR '24 | D107: 28 | E107: 8 | F107: 9 | G107: 27 | H107: OVERSTOCK | I107: 🔵 Sobra ang stock. Bawasan ang order.
C108: MAY '24 | D108: 27 | E108: 8 | F108: 9 | G108: 26 | H108: OVERSTOCK | I108: 🔵 Sobra ang stock. Bawasan ang order.
C109: JUN '24 | D109: 26 | E109: 6 | F109: 7 | G109: 25 | H109: EXCESS | I109: 🟣 Malabis na stock! Maaaring mag-expire.
C110: JUL '24 | D110: 25 | E110: 6 | F110: 7 | G110: 24 | H110: EXCESS | I110: 🟣 Malabis na stock! Maaaring mag-expire.
C111: AUG '24 | D111: 24 | E111: 5 | F111: 7 | G111: 22 | H111: OVERSTOCK | I111: 🔵 Sobra ang stock. Bawasan ang order.
C112: SEP '24 | D112: 22 | E112: 6 | F112: 7 | G112: 21 | H112: OVERSTOCK | I112: 🔵 Sobra ang stock. Bawasan ang order.
C113: OCT '24 | D113: 21 | E113: 7 | F113: 8 | G113: 20 | H113: OVERSTOCK | I113: 🔵 Sobra ang stock. Bawasan ang order.
C114: NOV '24 | D114: 20 | E114: 30 | F114: 8 | G114: 42 | H114: EXCESS | I114: 🟣 Malabis na stock! Maaaring mag-expire.
C115: DEC '24 | D115: 42 | E115: 25 | F115: 10 | G115: 57 | H115: EXCESS | I115: 🟣 Malabis na stock! Maaaring mag-expire.
C116: JAN '25 | D116: 57 | E116: 5 | F116: 6 | G116: 56 | H116: EXCESS | I116: 🟣 Malabis na stock! Maaaring mag-expire.
... C127: DEC '25 | D127: 64 | E127: 15 | F127: 13 | G127: 66 | H127: EXCESS | I127: 🟣 Malabis na stock! Maaaring mag-expire.
A129: Bleaching Powder | B129: packs | C129: JAN '24 | D129: 31 | E129: 6 | F129: 8 | G129: 29 | H129: EXCESS | I129: 🟣 Malabis na stock! Maaaring mag-expire.
C130: FEB '24 | D130: 29 | E130: 9 | F130: 10 | G130: 28 | H130: OVERSTOCK | I130: 🔵 Sobra ang stock. Bawasan ang order.
C131: MAR '24 | D131: 28 | E131: 10 | F131: 12 | G131: 26 | H131: OVERSTOCK | I131: 🔵 Sobra ang stock. Bawasan ang order.
C132: APR '24 | D132: 26 | E132: 10 | F132: 11 | G132: 25 | H132: OVERSTOCK | I132: 🔵 Sobra ang stock. Bawasan ang order.
C133: MAY '24 | D133: 25 | E133: 10 | F133: 12 | G133: 23 | H133: OK | I133: ✅ Stock level okay.
C134: JUN '24 | D134: 23 | E134: 7 | F134: 9 | G134: 21 | H134: OVERSTOCK | I134: 🔵 Sobra ang stock. Bawasan ang order.
C135: JUL '24 | D135: 21 | E135: 7 | F135: 8 | G135: 20 | H135: OVERSTOCK | I135: 🔵 Sobra ang stock. Bawasan ang order.
C136: AUG '24 | D136: 20 | E136: 6 | F136: 8 | G136: 18 | H136: OVERSTOCK | I136: 🔵 Sobra ang stock. Bawasan ang order.
C137: SEP '24 | D137: 18 | E137: 8 | F137: 9 | G137: 17 | H137: OK | I137: ✅ Stock level okay.
C138: OCT '24 | D138: 17 | E138: 8 | F138: 10 | G138: 15 | H138: OK | I138: ✅ Stock level okay.
C139: NOV '24 | D139: 15 | E139: 50 | F139: 12 | G139: 53 | H139: EXCESS | I139: 🟣 Malabis na stock! Maaaring mag-expire.
C140: DEC '24 | D140: 53 | E140: 30 | F140: 15 | G140: 68 | H140: EXCESS | I140: 🟣 Malabis na stock! Maaaring mag-expire.
C141: JAN '25 | D141: 68 | E141: 10 | F141: 8 | G141: 70 | H141: EXCESS | I141: 🟣 Malabis na stock! Maaaring mag-expire.
... C152: DEC '25 | D152: 96 | E152: 23 | F152: 17 | G152: 102 | H152: EXCESS | I152: 🟣 Malabis na stock! Maaaring mag-expire.
A154: Developer (20vol/30vol) | B154: liters | C154: JAN '24 | D154: 27 | E154: 7 | F154: 9 | G154: 25 | H154: OVERSTOCK | I154: 🔵 Sobra ang stock. Bawasan ang order.
C155: FEB '24 | D155: 25 | E155: 11 | F155: 12 | G155: 24 | H155: OK | I155: ✅ Stock level okay.
C156: MAR '24 | D156: 24 | E156: 10 | F156: 12 | G156: 22 | H156: OK | I156: ✅ Stock level okay.
C157: APR '24 | D157: 22 | E157: 10 | F157: 12 | G157: 20 | H157: OK | I157: ✅ Stock level okay.
C158: MAY '24 | D158: 20 | E158: 10 | F158: 12 | G158: 18 | H158: OK | I158: ✅ Stock level okay.
C159: JUN '24 | D159: 18 | E159: 8 | F159: 9 | G159: 17 | H159: OK | I159: ✅ Stock level okay.
C160: JUL '24 | D160: 17 | E160: 8 | F160: 10 | G160: 15 | H160: OK | I160: ✅ Stock level okay.
C161: AUG '24 | D161: 15 | E161: 7 | F161: 9 | G161: 13 | H161: OK | I161: ✅ Stock level okay.
C162: SEP '24 | D162: 13 | E162: 9 | F162: 10 | G162: 12 | H162: OK | I162: ✅ Stock level okay.
C163: OCT '24 | D163: 12 | E163: 9 | F163: 11 | G163: 10 | H163: OK | I163: ✅ Stock level okay.
C164: NOV '24 | D164: 10 | E164: 40 | F164: 14 | G164: 36 | H164: OVERSTOCK | I164: 🔵 Sobra ang stock. Bawasan ang order.
C165: DEC '24 | D165: 36 | E165: 20 | F165: 16 | G165: 40 | H165: OVERSTOCK | I165: 🔵 Sobra ang stock. Bawasan ang order.
C166: JAN '25 | D166: 40 | E166: 8 | F166: 9 | G166: 39 | H166: EXCESS | I166: 🟣 Malabis na stock! Maaaring mag-expire.
...

Sheet ABC Analysis
A1: ABC ANALYSIS — SERVICES (BY 2-YEAR REVENUE CONTRIBUTION)
A2: Pareto-based classification: Class A = top contributors making up ~80% of cumulative revenue (prioritize staffing/chemical stock), Class B = next ~15% (moderate priority), Class C = remaining ~5% (low priority / review necessity).
A3: Rank | B3: Service | C3: 2-Yr Revenue (₱) | D3: % of Total | E3: Cumulative % | F3: ABC Class | G3: Priority
A4: 1 | B4: Rebond, Cello, Haircut | C4: =SUM('Daily Data'!U4:U734) -> 1068481 | D4: =C4/$C$16 -> 0.34992009 | E4: =D4 -> 0.34992009 | F4: =IF(E4<=0.8,"A",IF(E4<=0.95,"B","C")) -> A | G4: =IF(F4="A","High - core revenue driver, prioritize chemical stock & skilled staff",IF(F4="B","Medium - maintain steady supply", "Low - monitor demand, optimize/replace if needed")) -> High - core revenue driver, prioritize chemical stock & skilled staff
A5: 2 | B5: Hair Color / Cellophane Treatment | C5: =SUM('Daily Data'!AC4:AC734) -> 598756 | D5: =C5/$C$16 -> 0.19608842 | E5: =E4+D5 -> 0.54600851 | F5: =IF(E5<=0.8,"A",IF(E5<=0.95,"B","C")) -> A | G5: =IF(F5="A","High - core revenue driver, prioritize chemical stock & skilled staff",IF(F5="B","Medium - maintain steady supply", "Low - monitor demand, optimize/replace if needed")) -> High - core revenue driver, prioritize chemical stock & skilled staff
A6: 3 | B6: Brazilian Collagen / Hair Botox | C6: =SUM('Daily Data'!AA4:AA734) -> 252201 | D6: =C6/$C$16 -> 0.082594072 | E6: =E5+D6 -> 0.62860259 | F6: =IF(E6<=0.8,"A",IF(E6<=0.95,"B","C")) -> A | G6: =IF(F6="A","High - core revenue driver, prioritize chemical stock & skilled staff",IF(F6="B","Medium - maintain steady supply", "Low - monitor demand, optimize/replace if needed")) -> High - core revenue driver, prioritize chemical stock & skilled staff
A7: 4 | B7: Haircut | C7: =SUM('Daily Data'!AI4:AI734) -> 201302 | D7: =C7/$C$16 -> 0.065925004 | E7: =E6+D7 -> 0.69452759 | F7: =IF(E7<=0.8,"A",IF(E7<=0.95,"B","C")) -> A | G7: =IF(F7="A","High - core revenue driver, prioritize chemical stock & skilled staff",IF(F7="B","Medium - maintain steady supply", "Low - monitor demand, optimize/replace if needed")) -> High - core revenue driver, prioritize chemical stock & skilled staff
A8: 5 | B8: Foot Spa | C8: =SUM('Daily Data'!AQ4:AQ734) -> 187935 | D8: =C8/$C$16 -> 0.061547405 | E8: =E7+D8 -> 0.756075 | F8: =IF(E8<=0.8,"A",IF(E8<=0.95,"B","C")) -> A | G8: =IF(F8="A","High - core revenue driver, prioritize chemical stock & skilled staff",IF(F8="B","Medium - maintain steady supply", "Low - monitor demand, optimize/replace if needed")) -> High - core revenue driver, prioritize chemical stock & skilled staff
A9: 6 | B9: Pedicure | C9: =SUM('Daily Data'!AO4:AO734) -> 173303 | D9: =C9/$C$16 -> 0.056755526 | E9: =E8+D9 -> 0.81283052 | F9: =IF(E9<=0.8,"A",IF(E9<=0.95,"B","C")) -> B | G9: =IF(F9="A","High - core revenue driver, prioritize chemical stock & skilled staff",IF(F9="B","Medium - maintain steady supply", "Low - monitor demand, optimize/replace if needed")) -> Medium - maintain steady supply
A10: 7 | B10: Manicure | C10: =SUM('Daily Data'!AM4:AM734) -> 166648 | D10: =C10/$C$16 -> 0.05457606 | E10: =E9+D10 -> 0.86740658 | F10: =IF(E10<=0.8,"A",IF(E10<=0.95,"B","C")) -> B | G10: =IF(F10="A","High - core revenue driver, prioritize chemical stock & skilled staff",IF(F10="B","Medium - maintain steady supply", "Low - monitor demand, optimize/replace if needed")) -> Medium - maintain steady supply
A11: 8 | B11: Protein Straightening Treatment | C11: =SUM('Daily Data'!Y4:Y734) -> 114477 | D11: =C11/$C$16 -> 0.037490421 | E11: =E10+D11 -> 0.904897 | F11: =IF(E11<=0.8,"A",IF(E11<=0.95,"B","C")) -> B | G11: =IF(F11="A","High - core revenue driver, prioritize chemical stock & skilled staff",IF(F11="B","Medium - maintain steady supply", "Low - monitor demand, optimize/replace if needed")) -> Medium - maintain steady supply
A12: 9 | B12: Cold Wave Perm | C12: =SUM('Daily Data'!AE4:AE734) -> 109451 | D12: =C12/$C$16 -> 0.035844441 | E12: =E11+D12 -> 0.94074144 | F12: =IF(E12<=0.8,"A",IF(E12<=0.95,"B","C")) -> B | G12: =IF(F12="A","High - core revenue driver, prioritize chemical stock & skilled staff",IF(F12="B","Medium - maintain steady supply", "Low - monitor demand, optimize/replace if needed")) -> Medium - maintain steady supply
A13: 10 | B13: Kilay (Eyebrow) | C13: =SUM('Daily Data'!AK4:AK734) -> 87612 | D13: =C13/$C$16 -> 0.02869232 | E13: =E12+D13 -> 0.96943376 | F13: =IF(E13<=0.8,"A",IF(E13<=0.95,"B","C")) -> C | G13: =IF(F13="A","High - core revenue driver, prioritize chemical stock & skilled staff",IF(F13="B","Medium - maintain steady supply", "Low - monitor demand, optimize/replace if needed")) -> Low - monitor demand, optimize/replace if needed
A14: 11 | B14: Rebond, Cello + Brazilian Collagen | C14: =SUM('Daily Data'!W4:W734) -> 75082 | D14: =C14/$C$16 -> 0.024588832 | E14: =E13+D14 -> 0.9940226 | F14: =IF(E14<=0.8,"A",IF(E14<=0.95,"B","C")) -> C | G14: =IF(F14="A","High - core revenue driver, prioritize chemical stock & skilled staff",IF(F14="B","Medium - maintain steady supply", "Low - monitor demand, optimize/replace if needed")) -> Low - monitor demand, optimize/replace if needed
A15: 12 | B15: Keratin Opti Straight | C15: =SUM('Daily Data'!AG4:AG734) -> 18252 | D15: =C15/$C$16 -> 0.005977403 | E15: =E14+D15 -> 1 | F15: =IF(E15<=0.8,"A",IF(E15<=0.95,"B","C")) -> C | G15: =IF(F15="A","High - core revenue driver, prioritize chemical stock & skilled staff",IF(F15="B","Medium - maintain steady supply", "Low - monitor demand, optimize/replace if needed")) -> Low - monitor demand, optimize/replace if needed
B16: TOTAL | C16: =SUM(C4:C15) -> 3053500 | D16: =SUM(D4:D15) -> 1
A38: ABC ANALYSIS — CHEMICAL INVENTORY (BY 2-YEAR USAGE VALUE)
A39: Usage Value = total units consumed over 24 months × estimated unit cost (₱). Class A items represent the highest peso-value consumption and warrant tighter stock control & reorder monitoring.
A40: Rank | B40: Chemical / Product | C40: Unit | D40: Est. Unit Cost (₱) | E40: Total Used (24mo) | F40: Usage Value (₱) | G40: % of Total | H40: ABC Class | I40: Cumulative %
A41: 1 | B41: Hair Color (Mixed Shades) | C41: tubes | D41: 250 | E41: 3213 | F41: =D41*E41 -> 803250 | G41: =F41/$F$48 -> 0.42770427 | H41: =IF(G41<=0.8,"A",IF(G41<=0.95,"B","C")) -> A | I41: =G41 -> 0.42770427
A42: 2 | B42: Rebonding Cream | C42: kits | D42: 850 | E42: 499 | F42: =D42*E42 -> 424150 | G42: =F42/$F$48 -> 0.22584596 | H42: =IF(I42<=0.8,"A",IF(I42<=0.95,"B","C")) -> A | I42: =I41+G42 -> 0.65355022
A43: 3 | B43: Cellophane Treatment | C43: sachets | D43: 120 | E43: 2666 | F43: =D43*E43 -> 319920 | G43: =F43/$F$48 -> 0.1703469 | H43: =IF(I43<=0.8,"A",IF(I43<=0.95,"B","C")) -> B | I43: =I42+G43 -> 0.82389713
A44: 4 | B44: Keratin Solution | C44: bottles | D44: 950 | E44: 195 | F44: =D44*E44 -> 185250 | G44: =F44/$F$48 -> 0.098639546 | H44: =IF(I44<=0.8,"A",IF(I44<=0.95,"B","C")) -> B | I44: =I43+G44 -> 0.92253667
A45: 5 | B45: Neutralizer | C45: bottles | D45: 180 | E45: 447 | F45: =D45*E45 -> 80460 | G45: =F45/$F$48 -> 0.04284231 | H45: =IF(I45<=0.8,"A",IF(I45<=0.95,"B","C")) -> C | I45: =I44+G45 -> 0.96537898
A46: 6 | B46: Developer (20vol/30vol) | C46: liters | D46: 160 | E46: 268 | F46: =D46*E46 -> 42880 | G46: =F46/$F$48 -> 0.022832193 | H46: =IF(I46<=0.8,"A",IF(I46<=0.95,"B","C")) -> C | I46: =I45+G46 -> 0.98821118
A47: 7 | B47: Bleaching Powder | C47: packs | D47: 90 | E47: 246 | F47: =D47*E47 -> 22140 | G47: =F47/$F$48 -> 0.011788824 | H47: =IF(I47<=0.8,"A",IF(I47<=0.95,"B","C")) -> C | I47: =I46+G47 -> 1
B48: TOTAL | F48: =SUM(F41:F47) -> 1878050 | G48: =SUM(G41:G47) -> 1
A49: Source: Estimated unit costs based on typical Philippine salon-supplier price lists (2025); usage volumes are model-generated from observed Nov2024-Apr2025 consumption rates, scaled with seasonal demand index.
